Workbook

Sheet Summary
A1: Computyme rules to deal with
A2: Every business rule in the 367 BP_Computyme programs, with source lines and a suggested tag. Work through the Rules tab: fill the yellow columns (Decision, Owner, PIV2 home, Notes).
A3: Example: IV.AUTO.ORDER.03 · Decision SIMPLIFY · Owner Mark · PIV2 home "Product page › Order (PO build)" · Notes "suggest by vendor, one PO per vendor".
A5: Domain | B5: Programs | C5: Rules | D5: KEEP | E5: SIMPLIFY | F5: QUESTION | G5: OBSOLETE | H5: OBSOLETE-INTEGRATION | I5: WAREHOUSE-ONLY | J5: Decided | K5: Open
A6: Vendors | B6: =COUNTIF(Programs!$B$2:$B$368,A6) -> 10 | C6: =COUNTIF(Rules!$C$2:$C$1568,A6) -> 26 | D6: =COUNTIFS(Rules!$C$2:$C$1568,$A6,Rules!$H$2:$H$1568,"KEEP") -> 10 | E6: =COUNTIFS(Rules!$C$2:$C$1568,$A6,Rules!$H$2:$H$1568,"SIMPLIFY") -> 4 | F6: =COUNTIFS(Rules!$C$2:$C$1568,$A6,Rules!$H$2:$H$1568,"QUESTION") -> 10 | G6: =COUNTIFS(Rules!$C$2:$C$1568,$A6,Rules!$H$2:$H$1568,"OBSOLETE") -> 2 | H6: =COUNTIFS(Rules!$C$2:$C$1568,$A6,Rules!$H$2:$H$1568,"OBSOLETE-INTEGRATION") -> 0 | I6: =COUNTIFS(Rules!$C$2:$C$1568,$A6,Rules!$H$2:$H$1568,"WAREHOUSE-ONLY") -> 0 | J6: =COUNTIFS(Rules!$C$2:$C$1568,A6,Rules!$I$2:$I$1568,"<>") -> 0 | K6: =C6-J6 -> 26
A7: AP | B7: =COUNTIF(Programs!$B$2:$B$368,A7) -> 10 | C7: =COUNTIF(Rules!$C$2:$C$1568,A7) -> 38 | D7: =COUNTIFS(Rules!$C$2:$C$1568,$A7,Rules!$H$2:$H$1568,"KEEP") -> 20 | E7: =COUNTIFS(Rules!$C$2:$C$1568,$A7,Rules!$H$2:$H$1568,"SIMPLIFY") -> 4 | F7: =COUNTIFS(Rules!$C$2:$C$1568,$A7,Rules!$H$2:$H$1568,"QUESTION") -> 8 | G7: =COUNTIFS(Rules!$C$2:$C$1568,$A7,Rules!$H$2:$H$1568,"OBSOLETE") -> 3 | H7: =COUNTIFS(Rules!$C$2:$C$1568,$A7,Rules!$H$2:$H$1568,"OBSOLETE-INTEGRATION") -> 3 | I7: =COUNTIFS(Rules!$C$2:$C$1568,$A7,Rules!$H$2:$H$1568,"WAREHOUSE-ONLY") -> 0 | J7: =COUNTIFS(Rules!$C$2:$C$1568,A7,Rules!$I$2:$I$1568,"<>") -> 0 | K7: =C7-J7 -> 38
A8: Products | B8: =COUNTIF(Programs!$B$2:$B$368,A8) -> 39 | C8: =COUNTIF(Rules!$C$2:$C$1568,A8) -> 129 | D8: =COUNTIFS(Rules!$C$2:$C$1568,$A8,Rules!$H$2:$H$1568,"KEEP") -> 63 | E8: =COUNTIFS(Rules!$C$2:$C$1568,$A8,Rules!$H$2:$H$1568,"SIMPLIFY") -> 9 | F8: =COUNTIFS(Rules!$C$2:$C$1568,$A8,Rules!$H$2:$H$1568,"QUESTION") -> 42 | G8: =COUNTIFS(Rules!$C$2:$C$1568,$A8,Rules!$H$2:$H$1568,"OBSOLETE") -> 10 | H8: =COUNTIFS(Rules!$C$2:$C$1568,$A8,Rules!$H$2:$H$1568,"OBSOLETE-INTEGRATION") -> 4 | I8: =COUNTIFS(Rules!$C$2:$C$1568,$A8,Rules!$H$2:$H$1568,"WAREHOUSE-ONLY") -> 1 | J8: =COUNTIFS(Rules!$C$2:$C$1568,A8,Rules!$I$2:$I$1568,"<>") -> 0 | K8: =C8-J8 -> 129
A9: Inventory | B9: =COUNTIF(Programs!$B$2:$B$368,A9) -> 37 | C9: =COUNTIF(Rules!$C$2:$C$1568,A9) -> 192 | D9: =COUNTIFS(Rules!$C$2:$C$1568,$A9,Rules!$H$2:$H$1568,"KEEP") -> 80 | E9: =COUNTIFS(Rules!$C$2:$C$1568,$A9,Rules!$H$2:$H$1568,"SIMPLIFY") -> 12 | F9: =COUNTIFS(Rules!$C$2:$C$1568,$A9,Rules!$H$2:$H$1568,"QUESTION") -> 62 | G9: =COUNTIFS(Rules!$C$2:$C$1568,$A9,Rules!$H$2:$H$1568,"OBSOLETE") -> 22 | H9: =COUNTIFS(Rules!$C$2:$C$1568,$A9,Rules!$H$2:$H$1568,"OBSOLETE-INTEGRATION") -> 0 | I9: =COUNTIFS(Rules!$C$2:$C$1568,$A9,Rules!$H$2:$H$1568,"WAREHOUSE-ONLY") -> 16 | J9: =COUNTIFS(Rules!$C$2:$C$1568,A9,Rules!$I$2:$I$1568,"<>") -> 0 | K9: =C9-J9 -> 192
A10: Orders | B10: =COUNTIF(Programs!$B$2:$B$368,A10) -> 59 | C10: =COUNTIF(Rules!$C$2:$C$1568,A10) -> 375 | D10: =COUNTIFS(Rules!$C$2:$C$1568,$A10,Rules!$H$2:$H$1568,"KEEP") -> 136 | E10: =COUNTIFS(Rules!$C$2:$C$1568,$A10,Rules!$H$2:$H$1568,"SIMPLIFY") -> 18 | F10: =COUNTIFS(Rules!$C$2:$C$1568,$A10,Rules!$H$2:$H$1568,"QUESTION") -> 147 | G10: =COUNTIFS(Rules!$C$2:$C$1568,$A10,Rules!$H$2:$H$1568,"OBSOLETE") -> 34 | H10: =COUNTIFS(Rules!$C$2:$C$1568,$A10,Rules!$H$2:$H$1568,"OBSOLETE-INTEGRATION") -> 18 | I10: =COUNTIFS(Rules!$C$2:$C$1568,$A10,Rules!$H$2:$H$1568,"WAREHOUSE-ONLY") -> 22 | J10: =COUNTIFS(Rules!$C$2:$C$1568,A10,Rules!$I$2:$I$1568,"<>") -> 0 | K10: =C10-J10 -> 375
A11: EDI | B11: =COUNTIF(Programs!$B$2:$B$368,A11) -> 9 | C11: =COUNTIF(Rules!$C$2:$C$1568,A11) -> 109 | D11: =COUNTIFS(Rules!$C$2:$C$1568,$A11,Rules!$H$2:$H$1568,"KEEP") -> 37 | E11: =COUNTIFS(Rules!$C$2:$C$1568,$A11,Rules!$H$2:$H$1568,"SIMPLIFY") -> 8 | F11: =COUNTIFS(Rules!$C$2:$C$1568,$A11,Rules!$H$2:$H$1568,"QUESTION") -> 54 | G11: =COUNTIFS(Rules!$C$2:$C$1568,$A11,Rules!$H$2:$H$1568,"OBSOLETE") -> 2 | H11: =COUNTIFS(Rules!$C$2:$C$1568,$A11,Rules!$H$2:$H$1568,"OBSOLETE-INTEGRATION") -> 8 | I11: =COUNTIFS(Rules!$C$2:$C$1568,$A11,Rules!$H$2:$H$1568,"WAREHOUSE-ONLY") -> 0 | J11: =COUNTIFS(Rules!$C$2:$C$1568,A11,Rules!$I$2:$I$1568,"<>") -> 0 | K11: =C11-J11 -> 109
A12: Members | B12: =COUNTIF(Programs!$B$2:$B$368,A12) -> 50 | C12: =COUNTIF(Rules!$C$2:$C$1568,A12) -> 180 | D12: =COUNTIFS(Rules!$C$2:$C$1568,$A12,Rules!$H$2:$H$1568,"KEEP") -> 72 | E12: =COUNTIFS(Rules!$C$2:$C$1568,$A12,Rules!$H$2:$H$1568,"SIMPLIFY") -> 9 | F12: =COUNTIFS(Rules!$C$2:$C$1568,$A12,Rules!$H$2:$H$1568,"QUESTION") -> 85 | G12: =COUNTIFS(Rules!$C$2:$C$1568,$A12,Rules!$H$2:$H$1568,"OBSOLETE") -> 12 | H12: =COUNTIFS(Rules!$C$2:$C$1568,$A12,Rules!$H$2:$H$1568,"OBSOLETE-INTEGRATION") -> 2 | I12: =COUNTIFS(Rules!$C$2:$C$1568,$A12,Rules!$H$2:$H$1568,"WAREHOUSE-ONLY") -> 0 | J12: =COUNTIFS(Rules!$C$2:$C$1568,A12,Rules!$I$2:$I$1568,"<>") -> 0 | K12: =C12-J12 -> 180
A13: AR | B13: =COUNTIF(Programs!$B$2:$B$368,A13) -> 77 | C13: =COUNTIF(Rules!$C$2:$C$1568,A13) -> 337 | D13: =COUNTIFS(Rules!$C$2:$C$1568,$A13,Rules!$H$2:$H$1568,"KEEP") -> 145 | E13: =COUNTIFS(Rules!$C$2:$C$1568,$A13,Rules!$H$2:$H$1568,"SIMPLIFY") -> 20 | F13: =COUNTIFS(Rules!$C$2:$C$1568,$A13,Rules!$H$2:$H$1568,"QUESTION") -> 114 | G13: =COUNTIFS(Rules!$C$2:$C$1568,$A13,Rules!$H$2:$H$1568,"OBSOLETE") -> 39 | H13: =COUNTIFS(Rules!$C$2:$C$1568,$A13,Rules!$H$2:$H$1568,"OBSOLETE-INTEGRATION") -> 18 | I13: =COUNTIFS(Rules!$C$2:$C$1568,$A13,Rules!$H$2:$H$1568,"WAREHOUSE-ONLY") -> 1 | J13: =COUNTIFS(Rules!$C$2:$C$1568,A13,Rules!$I$2:$I$1568,"<>") -> 0 | K13: =C13-J13 -> 337
A14: Reporting | B14: =COUNTIF(Programs!$B$2:$B$368,A14) -> 24 | C14: =COUNTIF(Rules!$C$2:$C$1568,A14) -> 123 | D14: =COUNTIFS(Rules!$C$2:$C$1568,$A14,Rules!$H$2:$H$1568,"KEEP") -> 11 | E14: =COUNTIFS(Rules!$C$2:$C$1568,$A14,Rules!$H$2:$H$1568,"SIMPLIFY") -> 10 | F14: =COUNTIFS(Rules!$C$2:$C$1568,$A14,Rules!$H$2:$H$1568,"QUESTION") -> 90 | G14: =COUNTIFS(Rules!$C$2:$C$1568,$A14,Rules!$H$2:$H$1568,"OBSOLETE") -> 11 | H14: =COUNTIFS(Rules!$C$2:$C$1568,$A14,Rules!$H$2:$H$1568,"OBSOLETE-INTEGRATION") -> 1 | I14: =COUNTIFS(Rules!$C$2:$C$1568,$A14,Rules!$H$2:$H$1568,"WAREHOUSE-ONLY") -> 0 | J14: =COUNTIFS(Rules!$C$2:$C$1568,A14,Rules!$I$2:$I$1568,"<>") -> 0 | K14: =C14-J14 -> 123
A15: Utility | B15: =COUNTIF(Programs!$B$2:$B$368,A15) -> 52 | C15: =COUNTIF(Rules!$C$2:$C$1568,A15) -> 58 | D15: =COUNTIFS(Rules!$C$2:$C$1568,$A15,Rules!$H$2:$H$1568,"KEEP") -> 5 | E15: =COUNTIFS(Rules!$C$2:$C$1568,$A15,Rules!$H$2:$H$1568,"SIMPLIFY") -> 5 | F15: =COUNTIFS(Rules!$C$2:$C$1568,$A15,Rules!$H$2:$H$1568,"QUESTION") -> 2 | G15: =COUNTIFS(Rules!$C$2:$C$1568,$A15,Rules!$H$2:$H$1568,"OBSOLETE") -> 43 | H15: =COUNTIFS(Rules!$C$2:$C$1568,$A15,Rules!$H$2:$H$1568,"OBSOLETE-INTEGRATION") -> 2 | I15: =COUNTIFS(Rules!$C$2:$C$1568,$A15,Rules!$H$2:$H$1568,"WAREHOUSE-ONLY") -> 1 | J15: =COUNTIFS(Rules!$C$2:$C$1568,A15,Rules!$I$2:$I$1568,"<>") -> 0 | K15: =C15-J15 -> 58
A16: Total | B16: =SUM(B6:B15) -> 367 | C16: =SUM(C6:C15) -> 1567 | D16: =SUM(D6:D15) -> 579 | E16: =SUM(E6:E15) -> 99 | F16: =SUM(F6:F15) -> 614 | G16: =SUM(G6:G15) -> 178 | H16: =SUM(H6:H15) -> 56 | I16: =SUM(I6:I15) -> 41 | ... K16: =SUM(K6:K15) -> 1567
A18: Relevance (programs)
A19: VENDOR | B19: =COUNTIF(Programs!$E$2:$E$368,"*VENDOR*") -> 82
A20: PRODUCT | B20: =COUNTIF(Programs!$E$2:$E$368,"*PRODUCT*") -> 129
A21: PO | B21: =COUNTIF(Programs!$E$2:$E$368,"*PO*") -> 63
A22: PRICING | B22: =COUNTIF(Programs!$E$2:$E$368,"*PRICING*") -> 89
A24: Tags: KEEP rebuild as is · SIMPLIFY right intent, cleaner build · QUESTION business must answer (every hard-coded member/vendor/product number) · OBSOLETE dead/retired (COO/CFO sign-off) · OBSOLETE-INTEGRATION legacy file format (CTO sign-off) · WAREHOUSE-ONLY stays with warehouse system. Source: github PhotographicResearchOrg/Extracted-rules, BP/.

Sheet Rules
A1: Rule ID | B1: Program | C1: Domain | D1: Mode | E1: Relevance | F1: Rule | G1: Source lines | H1: Suggested tag | I1: Decision | J1: Owner | K1: PIV2 home | L1: Notes
A2: AR17.01 | B2: AR17 | C2: Vendors | D2: Utility/maintenance | E2: VENDOR | F2: Hard-coded vendors 195 and 279: IVEND attr 4 (F4) = sum of AMOUNT (attr 2) and attr 5 (F5) = sum of SURCHG (attr 3) for those two vendors | G2: L1, L16-24 | H2: QUESTION
A3: IV2.01 | B3: IV2 | C3: Vendors | D3: Interactive | E3: VENDOR, PRICING | F3: New vendor number from CONTROL 'VEND' attr 1; counter incremented by 3 after each add | G3: L32, L177 | H3: QUESTION
A4: IV2.02 | B4: IV2 | C4: Vendors | D4: Interactive | E4: VENDOR, PRICING | F4: Hard-coded skipped vendor numbers 272, 713, 839, 902, 965 (if next number is one of these add 3) | G4: L12, L33 | H4: QUESTION
A5: IV2.03 | B5: IV2 | C5: Vendors | D5: Interactive | E5: VENDOR, PRICING | F5: A new vendor must first exist in APMST; name, address, city/state, zip, phone are copied from APMST attrs 1,3,4,5,6,7 | G5: L65-69 | H5: KEEP
A6: IV2.04 | B6: IV2 | C6: Vendors | D6: Interactive | E6: VENDOR, PRICING | F6: One APMST vendor may link to only one PRO vendor: VNIDX holds two-way index (vendor→APID and APID→vendor); duplicate rejected | G6: L70-71, L175-176 | H6: KEEP
A7: IV2.05 | B7: IV2 | C7: Vendors | D7: Interactive | E7: VENDOR, PRICING | F7: VNMST attr 12 APID = linked AP vendor | G7: L172 | H7: KEEP
A8: IV2.06 | B8: IV2 | C8: Vendors | D8: Interactive | E8: VENDOR, PRICING | F8: Validations: name 1-25 chars, name2 ≤25, street 1-25, city/state 1-22, zip exactly 5 digits, phone NNN-NNN-NNNN | G8: L76-124 | H8: SIMPLIFY
A9: IV2.07 | B9: IV2 | C9: Vendors | D9: Interactive | E9: VENDOR, PRICING | F9: Surcharge percent attr 8 stored in tenths of a percent (verify shows NI/10) | G9: L127-137 | H9: KEEP
A10: IV2.08 | B10: IV2 | C10: Vendors | D10: Interactive | E10: VENDOR, PRICING | F10: Surcharge type attr 6 (CODE), required when surcharge ≠ 0: 1 = surcharge rebated by vendor, 2 = surcharge added to vendor invoice | G10: L139-151 | H10: KEEP
A11: IV2.09 | B11: IV2 | C11: Vendors | D11: Interactive | E11: VENDOR, PRICING | F11: Vendor billing guarantee attr 13: 0 = none, 1 = vendor guarantees member billing | G11: L153-165 | H11: QUESTION
A12: IV46.9999.01 | B12: IV46.9999 | C12: Vendors | D12: Subroutine | E12: VENDOR, PO | F12: Misc vendor fields (name first; layout and validations defined in PROMPTS record, not in code) packed into INFO and stored on the PO | G12: L26-28, L55-63 | H12: QUESTION
A13: IV9.01 | B13: IV9 | C13: Vendors | D13: Report/print | E13: VENDOR | F13: Label = VNMST attr 1 NAME, 2 NAME2, 3 STREET, 4 CITY.STATE + 5 ZIP; quantity must be a multiple of 3; max 40 vendors | G13: L12-33 | H13: OBSOLETE
... A61: CUSTRBTNEW1.02 | B61: CUSTRBTNEW1 | C61: AP | D61: Test-variant | E61: PRODUCT | F61: No check-exists test: MATWRITE overwrites any existing RBTDATA record with the same number; no void path | G61: L74 | H61: QUESTION
A62: FIX.RBTCHK.01 | B62: FIX.RBTCHK | C62: AP | D62: Utility/maintenance | F62: Hard-coded: checks >= 35790 copied to new id '2' + chars 2-5 of old id (old record not deleted) | G62: L4-8 | H62: OBSOLETE
A63: LJ.CHK.TEST.01 | B63: LJ.CHK.TEST | C63: AP | D63: Test-variant | F63: Printer-test only; prints dummy payee/amount and MICR string 'C12345C A028000121A 261D050346C' (contains what looks like a routing/account number — confirm whether real) | G63: L16 | H63: OBSOLETE
A64: REBUILD.APBR.01 | B64: REBUILD.APBR | C64: AP | D64: Utility/maintenance | E64: VENDOR | F64: APDIST key ID[1,4] = AP vendor (APMST key); APBR record per check # (APDIST attr 15): attr 1 vendor, 2 vendor name (APMST attr 1), 3 date paid (APDIST attr 10), 4 sum gross (attr 3), 5 sum discount (attr 4), 6 net = gross - discount | G64: L8-19 | H64: KEEP
A65: REBUILD.APBR.02 | B65: REBUILD.APBR | C65: AP | D65: Utility/maintenance | E65: VENDOR | F65: Hard-coded saved list APDIST.JOHN (user-specific one-off) | G65: L5 | H65: OBSOLETE
A66: ADJ.ARHIST.01 | B66: ADJ.ARHIST | C66: Products | D66: Utility/maintenance | E66: PRODUCT, PRICING | F66: Average cost = INT(SUM(IVMST attr 25 AMT.RECD) / SUM(IVMST attr 24 QTY.REC)) when total received qty > 0 | G66: L13-14 | H66: QUESTION
A67: ADJ.ARHIST.02 | B67: ADJ.ARHIST | C67: Products | D67: Utility/maintenance | E67: PRODUCT, PRICING | F67: Fallback when nothing received: use IVMST attr 19 RAW cost; if RAW ends in "Y", cost = INT(numeric part / 110), else RAW as-is (the /110 implies "Y" means a 10% loaded price and a cents→dollars shift; units inconsistent with the other branch) | G67: L15-16 | H67: QUESTION
A68: ADJ.ARHIST.03 | B68: ADJ.ARHIST | C68: Products | D68: Utility/maintenance | E68: PRODUCT, PRICING | F68: ARHIST attr 15 (COST per ARSHIP naming) for each line = line qty (attr 3) × average cost | G68: L19 | H68: OBSOLETE
A69: BLD.IVMST.PW.01 | B69: BLD.IVMST.PW | C69: Products | D69: Outbound-generator | E69: PRODUCT, PRICING | F69: Only products with IVMST attr 36 DISPLAY ≠ "N" are exported (06-09-08) | G69: L6, L20 | H69: KEEP
A70: BLD.IVMST.PW.02 | B70: BLD.IVMST.PW | C70: Products | D70: Outbound-generator | E70: PRODUCT, PRICING | F70: Member price = ROUND(NET.1 (attr 8, cents) × (1000 + SCH.PCT) / 1000), i.e. surcharge percentage stored in tenths of a percent (SCH.PCT via include; IVMST dict attr 12 = PCT) | G70: L28-29 | H70: KEEP
A71: BLD.IVMST.PW.03 | B71: BLD.IVMST.PW | C71: Products | D71: Outbound-generator | E71: PRODUCT, PRICING | F71: Price exported in cents (MD2 conversion commented out); description tabs replaced by spaces | G71: L26, L30 | H71: QUESTION
A72: BLD.IVMST.PW.04 | B72: BLD.IVMST.PW | C72: Products | D72: Outbound-generator | E72: PRODUCT, PRICING | F72: Tab-delimited file staged as a PWDB record (07-02-08 replaced XML) | G72: L5, L18, L31-41 | H72: OBSOLETE-INTEGRATION
A73: BLD.IVMST.XML.01 | B73: BLD.IVMST.XML | C73: Products | D73: Outbound-generator | E73: PRODUCT, PRICING | F73: Same selection (DISPLAY ≠ "N") and price formula ROUND(NET.1 × (1000 + SCH.PCT)/1000) as BLD.IVMST.PW, but price output in dollars (MD2) | G73: L22, L29-31 | H73: KEEP
A74: BLD.IVMST.XML.02 | B74: BLD.IVMST.XML | C74: Products | D74: Outbound-generator | E74: PRODUCT, PRICING | F74: XML layout (INVENTORY/DETAIL with Product, Description CDATA, Cost, optional Multiple/Status/UPC) staged in PWDB | G74: L20, L32-43 | H74: OBSOLETE-INTEGRATION
A75: BUILD.IVCAT.01 | B75: BUILD.IVCAT | C75: Products | D75: Utility/maintenance | E75: PRODUCT | F75: Hard-coded UPC prefix "0291440" + PRO product number + UPC-A check digit (odd positions ×3 + even, check = round-up-to-10 − total) | G75: L11-21 | H75: QUESTION
... A360: IVPO.ON.ORD.01 | B360: IVPO.ON.ORD | C360: Inventory | D360: Subroutine | E360: PO | F360: For each value I: on-order = QO<1,I> − SUM(QR<1,I>) (ordered minus all received sub-values) | G360: L2-5 | H360: KEEP
A361: I_BLD.MEQHIST.01 | B361: I_BLD.MEQHIST | C361: Inventory | D361: Subroutine | F361: MEQHIST entries whose key date (first '*' field, internal date) is older than TODAY-30 are deleted (30-day retention) | G361: L5-16 | H361: WAREHOUSE-ONLY
A362: I_BLD.MEQHIST.02 | B362: I_BLD.MEQHIST | C362: Inventory | D362: Subroutine | F362: Header record MEQDATA 'RECS' (default '0,0') holds the record count in its 2nd comma field; it is copied to MEQHIST key TODAY*TIME*RECS, then each MEQDATA record 1..RECS is copied to MEQHIST key TODAY*TIME*n | G362: L17-31 | H362: WAREHOUSE-ONLY
A363: I_IV46_COMMON.01 | B363: I_IV46_COMMON | C363: Inventory | D363: Subroutine | E363: PO | F363: PO header context carried in COMMON: PO number, PO date, primary vendor number+name and second vendor number+name (SVND purpose not stated here) | G363: L2 | H363: QUESTION
A364: I_IV46_COMMON.02 | B364: I_IV46_COMMON | C364: Inventory | D364: Subroutine | E364: PO | F364: Fixed file-handle slot map (FILES(1..23): PROMPTS, SCREENS, APMST, ARMST, CONTROL, CUSTIDX, IVCAT, IVCUST, IVEMP, IVINV, IVSOLD, IVMST, THROWAYS, ZIPPREF, TERMINALS, APIDX, TREES, IVORD, IVPO, IVNEW, IVSPORD) | G364: L7-29 | H364: OBSOLETE
A365: I_MEQ.ERROR.01 | B365: I_MEQ.ERROR | C365: Inventory | D365: Report/print | E365: PRODUCT | F365: Error report lists Emp, Store, Seq, Product, Qty, message and the prior record's product + description (IVINV attr 6 description, else IVMST attr 3 — attr 3 per D_IVMST is REQ, so "attr 3 (purpose unclear)" used as description) | G365: L13-38 | H365: WAREHOUSE-ONLY
A366: I_MEQ.ERROR.02 | B366: I_MEQ.ERROR | C366: Inventory | D366: Report/print | E366: PRODUCT | F366: Catalog-number resolution fallback: look up IVCAT with full product; if length < 10 use as is; else try substrings [2,10], [2,12], [1,10], [1,11]; else use raw value | G366: L69-82 | H366: SIMPLIFY
A367: I_MEQ.ERROR.03 | B367: I_MEQ.ERROR | C367: Inventory | D367: Report/print | E367: PRODUCT | F367: ERROR file entries are purged when the date in the 4th '.'-field of the key + 185 days < today (comment at L5 says 120 days) | G367: L83-94 | H367: QUESTION
A368: LOOKUP.01 | B368: LOOKUP | C368: Inventory | D368: Interactive | E368: PRODUCT | F368: PARTS record: attr 1 = location, attr 2 = description (lens parts) | G368: L12-13 | H368: WAREHOUSE-ONLY
A369: PO.DISC.01 | B369: PO.DISC | C369: Inventory | D369: Batch | E369: PO, PRODUCT, PRICING | F369: IVPO line is open when qty ordered (IVPO attr 7) > total received (sum of IVPO attr 9 subvalues via SUMM) | G369: L28-29 | H369: KEEP
A370: PO.DISC.02 | B370: PO.DISC | C370: Inventory | D370: Batch | E370: PO, PRODUCT, PRICING | F370: Open IVPO line whose PO # is not in IVMST attr 20 is appended to IVMST: PO # -> attr 20, PO cost (IVPO attr 8, cents) -> attr 22 (PO.CST, added 01-09-12) | G370: L37-39,98-102 | H370: KEEP
A371: PO.DISC.03 | B371: PO.DISC | C371: Inventory | D371: Batch | E371: PO, PRODUCT, PRICING | F371: If nothing received yet (IVPO attr 9 blank): IVMST attr 21 = qty ordered, attr 23 = blank; if partially received: attr 21 = blank and attr 23 (backorder) = ordered - received | G371: L100-110 | H371: QUESTION
A372: PO.DISC.04 | B372: PO.DISC | C372: Inventory | D372: Batch | E372: PO, PRODUCT, PRICING | F372: Product on IVPO not in IVMST but whose IVPO attr 14 special-order id exists in IVSPORD is booked against hard-coded catch-all product 555 | G372: L42-48 | H372: QUESTION
A373: PO.DISC.05 | B373: PO.DISC | C373: Inventory | D373: Batch | E373: PO, PRODUCT, PRICING | F373: IVPO product found in neither IVMST nor IVSPORD is only reported ("NOT FOUND ON IVMST OR IVSPORD"), no fix | G373: L51 | H373: KEEP
A374: PO.DISC.06 | B374: PO.DISC | C374: Inventory | D374: Batch | E374: PO, PRODUCT, PRICING | F374: Pass 2: for every IVMST PO entry, delete it (attrs 20-23 at that position) if PO not on IVPO, if product not on that PO and no IVSPORD record, or if received >= ordered | G374: L74-90,115-121 | H374: KEEP
... A397: AUTO.ORDER.11 | B397: AUTO.ORDER | C397: Orders | D397: Staging-processor | E397: VENDOR, PRODUCT, PO, PRICING | F397: Order discount (attr 11) is stored but not applied to cost | G397: L69, L79-82 | H397: QUESTION
A398: BLD.SCANORD.UPS.01 | B398: BLD.SCANORD.UPS | C398: Orders | D398: Staging-processor | F398: Every run first clears tracking #, packages, published cost and negotiated cost on ALL SCANORD records, then rebuilds (10-14-11) | G398: L5, L20-32 | H398: SIMPLIFY
A399: BLD.SCANORD.UPS.02 | B399: BLD.SCANORD.UPS | C399: Orders | D399: Staging-processor | F399: UPS export staging: records whose key starts "EXP" hold CSV lines (line 1 header); columns 1 SCANORD id, 2 tracking #, 3 published cost, 4 negotiated cost (dollars → cents via MD2), 5 package count, 6 void flag | G399: L36-43, L63-70, L86-88 | H399: OBSOLETE-INTEGRATION
A400: BLD.SCANORD.UPS.03 | B400: BLD.SCANORD.UPS | C400: Orders | D400: Staging-processor | F400: Voided shipments (col 6 = "Y") are ignored | G400: L7, L67-68 | H400: KEEP
A401: BLD.SCANORD.UPS.04 | B401: BLD.SCANORD.UPS | C401: Orders | D401: Staging-processor | F401: Each new tracking # appended to SCANORD attr 15 with matching packages (16), published cost (17), negotiated cost (18); duplicates skipped | G401: L92-98 | H401: WAREHOUSE-ONLY
A402: BLD.SCANORD.UPS.05 | B402: BLD.SCANORD.UPS | C402: Orders | D402: Staging-processor | F402: For multi-package shipments, package counts and costs are summed into single totals while all tracking numbers are kept | G402: L46-57, L103-129 | H402: WAREHOUSE-ONLY
A403: CHANGE.INST.01 | B403: CHANGE.INST | C403: Orders | D403: Interactive | E403: PO | F403: Order must exist in ORDHIST and its member in ARMST | G403: L28-29 | H403: KEEP
A404: CHANGE.INST.02 | B404: CHANGE.INST | C404: Orders | D404: Interactive | E404: PO | F404: "Dated" orders — special instructions (attr 9) starting with "1" or "2" — cannot be changed | G404: L30 | H404: KEEP
A405: CHANGE.INST.03 | B405: CHANGE.INST | C405: Orders | D405: Interactive | E405: PO | F405: No change allowed once any VNORD record for the order has a STATUS (attr 12) value (order started) | G405: L63-73 | H405: KEEP
A406: CHANGE.INST.04 | B406: CHANGE.INST | C406: Orders | D406: Interactive | E406: PO | F406: Instructions = two lines of max 24 chars joined by a space; line 1 cannot start with 1 or 2; shortcut "D1" → "1st Dated Order", "D2" → "2nd Dated Order" (which then makes the order a dated order) | G406: L37-58 | H406: QUESTION
A407: CHANGE.INST.05 | B407: CHANGE.INST | C407: Orders | D407: Interactive | E407: PO | F407: New instructions written to every VNORD for the order (attr 7 INST), ORDHIST attr 9 and IVORD attr 9 | G407: L75-90 | H407: KEEP
A408: CHANGE.VNORD.01 | B408: CHANGE.VNORD | C408: Orders | D408: Utility/maintenance | E408: VENDOR, PRODUCT, PO | F408: Old vendor must exist in VNMST; product in IVMST; new vendor = IVMST attr 5 VENDOR | G408: L12-15, L39 | H408: KEEP
A409: CHANGE.VNORD.02 | B409: CHANGE.VNORD | C409: Orders | D409: Utility/maintenance | E409: VENDOR, PRODUCT, PO | F409: Product line (VNORD attr 2 product, attr 3 qty) removed from old vendor order; old VNORD deleted if no lines remain | G409: L22-35 | H409: KEEP
A410: CHANGE.VNORD.03 | B410: CHANGE.VNORD | C410: Orders | D410: Utility/maintenance | E410: VENDOR, PRODUCT, PO | F410: New VNORD key = new vendor : chars 4-10 of old key (assumes 3-digit vendor prefix); line appended to existing new-vendor order or a new one created copying header attrs 1, 4-11 | G410: L39-44 | H410: QUESTION
A411: CHANGE.VNORD.04 | B411: CHANGE.VNORD | C411: Orders | D411: Utility/maintenance | E411: VENDOR, PRODUCT, PO | F411: Hard-coded product group 10 (IVMST attr 6): VNORD attr 8 value 2 qty moved with the line | G411: L33, L42-43 | H411: QUESTION
A412: CHANGE.VNORD.05 | B412: CHANGE.VNORD | C412: Orders | D412: Utility/maintenance | E412: VENDOR, PRODUCT, PO | F412: NUMBER records whose VN is one of the changed vendor orders get attr 4 = new vendor (NUMBER purpose not documented here) | G412: L48-59 | H412: QUESTION
A413: CHG.DATING.01 | B413: CHG.DATING | C413: Orders | D413: Utility/maintenance | E413: PO | F413: Dated status is stored as text in special instructions: "1st Dated Order", "2nd Dated Order" or blank (other instructions are overwritten) | G413: L18-24 | H413: QUESTION
A414: CHG.DATING.02 | B414: CHG.DATING | C414: Orders | D414: Utility/maintenance | E414: PO | F414: Same value written to IVORD attr 9, ORDHIST attr 9 and every VNORD attr 7 for the order, with no started-order check (unlike CHANGE.INST) | G414: L23-28 | H414: QUESTION
... A429: DEL.NUMBER.03 | B429: DEL.NUMBER | C429: Orders | D429: Utility/maintenance | E429: PO | F429: After deleting the shipping number, VNORD attr 12 STATUS reset to 0 (meaning of status codes unclear) | G429: L19-20 | H429: QUESTION
A430: ENV.1.01 | B430: ENV.1 | C430: Orders | D430: Interactive | F430: New envelope number from DICT PRO.ENV 'ENV' attr 2, incremented | G430: L26-29 | H430: OBSOLETE
A431: ENV.1.02 | B431: ENV.1 | C431: Orders | D431: Interactive | F431: Ship date defaults to today, may not be more than 3 days in the future | G431: L66-71 | H431: OBSOLETE
A432: ENV.1.03 | B432: ENV.1 | C432: Orders | D432: Interactive | F432: Ship type M=Mail, U=UPS, N=Next Day UPS; origin A=Abington, H=Huntingdon Valley (hard-coded office locations) | G432: L84-100,L130-135 | H432: OBSOLETE
A433: ENV.1.04 | B433: ENV.1 | C433: Orders | D433: Interactive | F433: On exit, deletes envelopes with SHIP.DATE older than today-12 days | G433: L137-151 | H433: OBSOLETE
A434: FIX.CAN.UPS.01 | B434: FIX.CAN.UPS | C434: Orders | D434: Utility/maintenance | F434: Master and dependent shipping numbers must exist in SCANORD | G434: L13-24 | H434: WAREHOUSE-ONLY
A435: FIX.CAN.UPS.02 | B435: FIX.CAN.UPS | C435: Orders | D435: Utility/maintenance | F435: Combine: dependent lines removed from UPS_DOM; dependent numbers inserted after CSV column 14 of the master line; UPS_INT dependent lines re-keyed to master number | G435: L25-64 | H435: WAREHOUSE-ONLY
A436: FIX.CAN.UPS.03 | B436: FIX.CAN.UPS | C436: Orders | D436: Utility/maintenance | F436: Filename-keyed CSV staging records in file UPS (UPS_DOM.CSV, UPS_DOM_2.CSV, UPS_DOM_4.CSV, same for UPS_INT) all overwritten with the same content | G436: L41-43,L62-72 | H436: OBSOLETE-INTEGRATION
A437: FIX.COST.01 | B437: FIX.COST | C437: Orders | D437: Utility/maintenance | E437: PRICING, PRODUCT | F437: Line price = INT(('1.0' concatenated with IVMST attr 12 PCT) x unit cost + .5); the markup factor is built by string concatenation (PCT 5 → 1.05, but PCT 12 → 1.012) | G437: L14-18 | H437: QUESTION
A438: FIX.COST.02 | B438: FIX.COST | C438: Orders | D438: Utility/maintenance | E438: PRICING, PRODUCT | F438: Quantity break: if IVMST attr 7 QUAN > 0 and order qty >= QUAN and attr 9 NET.2 > 0 use NET.2, else attr 8 NET.1/COST (cents) | G438: L15-19 | H438: KEEP
A439: FIX.COST.03 | B439: FIX.COST | C439: Orders | D439: Utility/maintenance | E439: PRICING, PRODUCT | F439: IVORD attr 4 COST per line set; attr 10 COST.QTY = sum(qty x price) | G439: L20-24 | H439: OBSOLETE
A440: FIX.DUP.PROD.01 | B440: FIX.DUP.PROD | C440: Orders | D440: Utility/maintenance | E440: PO, PRODUCT | F440: Creates I-descriptor DUP.PROD = COUNT(PROD,<product>) in SCANORD/ORDHIST dicts to find orders with the product more than once | G440: L30-34,L54-58 | H440: OBSOLETE
A441: FIX.DUP.PROD.02 | B441: FIX.DUP.PROD | C441: Orders | D441: Utility/maintenance | E441: PO, PRODUCT | F441: Second occurrence's prod/qty/cost removed; COST.QTY<1> -= cost x qty and COST.QTY<2> -= qty | G441: L108-121,L144-157,L180-194 | H441: OBSOLETE
A442: FIX.DUP.PROD.03 | B442: FIX.DUP.PROD | C442: Orders | D442: Utility/maintenance | E442: PO, PRODUCT | F442: Hard-coded vendor 497 prefixed to ORDHIST order to form the VNORD key (VNORD key = vendor:order); SCANORD VORD minus 3-char prefix = IVORD order | G442: L64,L88-91 | H442: QUESTION
A443: IV.INP.SCANORD.01 | B443: IV.INP.SCANORD | C443: Orders | D443: Interactive | E443: PRODUCT | F443: Employee # (max 4 digits) must exist in IVEMP | G443: L85-91 | H443: WAREHOUSE-ONLY
A444: IV.INP.SCANORD.02 | B444: IV.INP.SCANORD | C444: Orders | D444: Interactive | E444: PRODUCT | F444: Shipping number must exist in NUMBER; order = NUMBER attr 4 VENDOR : attr 2 ORDER → VNORD key; skip if VNORD locked or missing | G444: L98-110 | H444: WAREHOUSE-ONLY
A445: IV.INP.SCANORD.03 | B445: IV.INP.SCANORD | C445: Orders | D445: Interactive | E445: PRODUCT | F445: Future shipment hold: if VNORD attr 6 SHIP (ship-after date) > today-1 (i.e. today or later) scanning requires hard-coded override code 'THE.CODE' | G445: L111-116 | H445: QUESTION
A446: IV.INP.SCANORD.04 | B446: IV.INP.SCANORD | C446: Orders | D446: Interactive | E446: PRODUCT | F446: New SCANORD record: 1 prods, 2 qty ordered (from VNORD 2/3), 4 emp, 5 date, 6 start times (MV per session), 8 member, 11 status 'O', 12 VNORD key, 13 type (NUMBER attr 3) | G446: L117-129 | H446: WAREHOUSE-ONLY
A447: IV.INP.SCANORD.05 | B447: IV.INP.SCANORD | C447: Orders | D447: Interactive | E447: PRODUCT | F447: Already billed (SCANORD attr 10 BILLED set) shipments cannot be rescanned; closed ('C') can be reopened with "O" | G447: L130-140 | H447: KEEP
A448: IV.INP.SCANORD.06 | B448: IV.INP.SCANORD | C448: Orders | D448: Interactive | E448: PRODUCT | F448: VNORD attr 12 STATUS set to 2 when scanning starts | G448: L141-142 | H448: QUESTION
... A457: IV.INP.SCANORD.15 | B457: IV.INP.SCANORD | C457: Orders | D457: Interactive | E457: PRODUCT | F457: UPS staging update via UPD.UPS when UPS/UPS.IDX files and CONTROL 'UPS.PARAMS' exist | G457: L68-75,L261 | H457: OBSOLETE-INTEGRATION
A458: IV.INP.SHPCHG.01 | B458: IV.INP.SHPCHG | C458: Orders | D458: Interactive | F458: Shipments with SCANORD attr 11 STATUS = "NS" (no shipping) are presented; operator enters amount (##.## or whole dollars via MONEY, stored cents) or S to skip | G458: L12-15,L26-33 | H458: KEEP
A459: IV.INP.SHPCHG.02 | B459: IV.INP.SHPCHG | C459: Orders | D459: Interactive | F459: Zero shipping must be confirmed by re-entering 0 | G459: L35-38 | H459: KEEP
A460: IV.INP.SHPCHG.03 | B460: IV.INP.SHPCHG | C460: Orders | D460: Interactive | F460: Non-zero charge: add line product 9999 (hard-coded shipping product) qty ordered 1, shipped 1; attr 9 SHIPPING = charge; status → 'C' | G460: L44-47 | H460: QUESTION
A461: IV.PRT.PACKLIST.01 | B461: IV.PRT.PACKLIST | C461: Orders | D461: Report/print | E461: VENDOR, PRICING | F461: Shipping number may be entered as "SN*MASTER" (Canada master shipment) | G461: L4, L29 | H461: QUESTION
A462: IV.PRT.PACKLIST.02 | B462: IV.PRT.PACKLIST | C462: Orders | D462: Report/print | E462: VENDOR, PRICING | F462: SCANORD attr 12 holds the VNORD key (vendor 3 + order 5); SCANORD attr 1/2/3 = product/qty ordered/qty shipped; backorder = ordered − shipped | G462: L37-39, L69-70 | H462: KEEP
A463: IV.PRT.PACKLIST.03 | B463: IV.PRT.PACKLIST | C463: Orders | D463: Report/print | E463: VENDOR, PRICING | F463: SCANORD attr 13 = 'B' labels the order as a BACKORDER | G463: L49 | H463: KEEP
A464: IV.PRT.PACKLIST.04 | B464: IV.PRT.PACKLIST | C464: Orders | D464: Report/print | E464: VENDOR, PRICING | F464: Checked-by = SCANORD attr 4 (EMP) | G464: L64 | H464: WAREHOUSE-ONLY
A465: IV.PRT.PACKLIST.05 | B465: IV.PRT.PACKLIST | C465: Orders | D465: Report/print | E465: VENDOR, PRICING | F465: Terms: billing month = next month, +1 more if today's day > 25; due day the 10th | G465: L108-110, L130 | H465: QUESTION
A466: IV.PRT.PACKLIST.06 | B466: IV.PRT.PACKLIST | C466: Orders | D466: Report/print | E466: VENDOR, PRICING | F466: Future-dating (FTR) from VNMST attr 17 (FTR), else IVORD attr 12; terms % from VNMST attr 16, else IVORD attr 11 (DISC). If FTR date > the 10th of billing month, months offset = FTR month − billing month (wrap 12) else 0 | G466: L111-122 | H466: QUESTION
A467: IV.PRT.PACKLIST.07 | B467: IV.PRT.PACKLIST | C467: Orders | D467: Report/print | E467: VENDOR, PRICING | F467: Terms text: "<pct>% MM/10/YY" when terms ≠ 0, else "NET MM/10/YY" using billing month | G467: L124-130 | H467: QUESTION
A468: IV.PRT.PACKLIST.08 | B468: IV.PRT.PACKLIST | C468: Orders | D468: Report/print | E468: VENDOR, PRICING | F468: Ship-to precedence VNORD 9/10 → ARMST 31/32 → ARMST bill address; "CHARGE SHIPPING" unless VNORD attr 8 > 0 | G468: L45-47, L67 | H468: QUESTION
A469: IV.PRT.PACKLIST.09 | B469: IV.PRT.PACKLIST | C469: Orders | D469: Report/print | E469: VENDOR, PRICING | F469: Hard-coded "PRO WAREHOUSE, 2950 Turnpike Drive, Hatboro PA 19040" | G469: L21-22 | H469: OBSOLETE
A470: IV.PRT.PACKLIST.CT.01 | B470: IV.PRT.PACKLIST.CT | C470: Orders | D470: Test-variant | F470: Header from ORDHIST: member attr 1, order date attr 6, ship-after attr 8, instructions attr 9, ship-to attr 19/20, attr 18 (TORD) for shipping flag | G470: L34-62 | H470: KEEP
A471: IV.PRT.PACKLIST.CT.02 | B471: IV.PRT.PACKLIST.CT | C471: Orders | D471: Test-variant | F471: Terms are not reprinted (left blank) | G471: L50-51 | H471: QUESTION
A472: IV.PRT.PACKLIST.CT.03 | B472: IV.PRT.PACKLIST.CT | C472: Orders | D472: Test-variant | F472: Shipping charge flag: blank when ORDHIST attr 18 > 0 or empty | G472: L62 | H472: QUESTION
A473: IV.PRT.PACKLIST.CT.04 | B473: IV.PRT.PACKLIST.CT | C473: Orders | D473: Test-variant | F473: Ship date from SCANORD attr 5 | G473: L60 | H473: KEEP
A474: IV.SCAN.ORD.01 | B474: IV.SCAN.ORD | C474: Orders | D474: Utility/maintenance | F474: Program body is only "$ USE IV.INP.SCANORD"; no logic of its own | G474: L1 | H474: OBSOLETE
A475: IV.UPD.BILLPEND.01 | B475: IV.UPD.BILLPEND | C475: Orders | D475: Utility/maintenance | F475: Program body is only "$ USE IV.UPD.SCANORD"; no logic of its own | G475: L1 | H475: OBSOLETE
...

Sheet Programs
A1: Program | B1: Domain | C1: Mode | D1: Lines | E1: Relevance | F1: Rules | G1: Questions | H1: Purpose | I1: Files | J1: Calls | K1: Bugs / oddities
A2: 28200.RPT | B2: Reporting | C2: Report/print | D2: 40 | E2: PRODUCT | F2: =COUNTIF(Rules!$B$2:$B$1568,A2) -> 5 | G2: =COUNTIFS(Rules!$B$2:$B$1568,A2,Rules!$H$2:$H$1568,"QUESTION") -> 2 | H2: Builds a per-member TEMPDATA summary of quantity and amount sold for four hard-coded Olympus products from a date range of TEMPHIST (ARHIST copy). | I2: reads TEMPHIST (opened as ARHIST) · writes TEMPDATA (cleared first) | J2: EXECUTE CLEAR-FILE DATA TEMPDATA; EXECUTE SSELECT TEMPHIST | K2: TEMPDATA is cleared on every date-range loop; line loop hard-capped at 800 and stops at first blank product; reads TEMPHIST not ARHIST despite the variable name; amount units not stated (whatever ARHIST attr 4 holds, likely cents).
A3: ADJ | B3: Members | C3: Utility/maintenance | D3: 9 | F3: =COUNTIF(Rules!$B$2:$B$1568,A3) -> 1 | G3: =COUNTIFS(Rules!$B$2:$B$1568,A3,Rules!$H$2:$H$1568,"QUESTION") -> 1 | H3: Manually decrements a member's STOCK warehouse-profit figure by an operator-entered amount. | I3: reads STOCK · writes STOCK | J3: none | K3: READV without lock then WRITEV (lost-update risk); invalid member silently re-prompts; no numeric check on amount.
A4: ADJ.ARHIST | B4: Products | C4: Utility/maintenance | D4: 25 | E4: PRODUCT, PRICING | F4: =COUNTIF(Rules!$B$2:$B$1568,A4) -> 3 | G4: =COUNTIFS(Rules!$B$2:$B$1568,A4,Rules!$H$2:$H$1568,"QUESTION") -> 2 | H4: One-off fix-up that recalculates the cost field (attr 15) on ARHIST lines for returns using IVMST average received cost. | I4: reads ARHIST, IVMST · writes ARHIST | J4: none (relies on an active select list) | K4: Header says "for returns" but nothing filters returns (depends on whatever list is active); MATREADU ELSE GO 5 conflates not-found and locked; RAW "Y" suffix convention is undocumented; mixed money units between branches.
A5: AP.SEL.INVSPC | B5: AP | C5: Interactive | D5: 126 | E5: VENDOR, PRICING | F5: =COUNTIF(Rules!$B$2:$B$1568,A5) -> 11 | G5: =COUNTIFS(Rules!$B$2:$B$1568,A5,Rules!$H$2:$H$1568,"QUESTION") -> 2 | H5: Selects all unpaid AP invoices for one vendor for payment while taking an extra "special" discount off each invoice. | I5: reads APDIST, APHIST, APDUE, APMST, CONTROL · writes APDIST, APHIST, APDUE, CONTROL (APCHK) | J5: CALL IDATE | K5: Held credits left in the list at end of run are never written (lost); held items use APHIST key FIELD(id,'*',1,2) while main path uses full ID — inconsistent keys; error prefix says "AP9"; MATREADU ELSE treats locked as not-found.
A6: AP10 | B6: AP | C6: Interactive | D6: 38 | E6: VENDOR | F6: =COUNTIF(Rules!$B$2:$B$1568,A6) -> 4 | G6: =COUNTIFS(Rules!$B$2:$B$1568,A6,Rules!$H$2:$H$1568,"QUESTION") -> 1 | H6: Cancels the entire pending AP payment selection and reverses special discounts. | I6: reads CONTROL, APDUE, APDIST, APHIST · writes APDIST, APHIST, CONTROL; deletes APDUE | J6: none | K6: Any read failure CHAINs to ABORT mid-run leaving a partially reversed selection; reverses using APHIST key = APDUE ID whereas AP.SEL.INVSPC held-credit path wrote APHIST under FIELD(id,'*',1,2).
A7: AR.ADJ.CY | B7: AR | C7: Utility/maintenance | D7: 18 | F7: =COUNTIF(Rules!$B$2:$B$1568,A7) -> 2 | G7: =COUNTIFS(Rules!$B$2:$B$1568,A7,Rules!$H$2:$H$1568,"QUESTION") -> 2 | H7: Year-roll/reset style fix-up that sets every member's current-year high credit to the current balance. | I7: reads ARMST · writes ARMST | J7: UPD.ARLOG (commented out) | K7: ARLOG audit call commented out despite the 07-23-09 note adding it; units differ between fields (cents vs dollars); MATREADU ELSE silently skips locked records.
A8: AR.CHANGE | B8: AR | C8: Utility/maintenance | D8: 10 | F8: =COUNTIF(Rules!$B$2:$B$1568,A8) -> 2 | G8: =COUNTIFS(Rules!$B$2:$B$1568,A8,Rules!$H$2:$H$1568,"QUESTION") -> 1 | H8: One-off script that re-keys selected ARHIST records to member 2829 (moves history from one member to another). | I8: reads ARHIST · writes ARHIST (write new, delete old) | J8: none (needs active select list) | K8: Silent overwrite of existing history under target key; READU ELSE conflates locked/missing.
A9: AR.INP.DEPTICK | B9: AR | C9: Interactive | D9: 433 | F9: =COUNTIF(Rules!$B$2:$B$1568,A9) -> 10 | G9: =COUNTIFS(Rules!$B$2:$B$1568,A9,Rules!$H$2:$H$1568,"QUESTION") -> 3 | H9: Enters and edits cash deposit tickets (member account, check number, check amount per line) that payments are later applied against. | I9: reads ARMST, DEPTICK, CONTROL, SCREENS · writes DEPTICK, CONTROL ('DEPTICK' counter) | J9: RAWINPUT, IDATE, MONEY, SUMM; INCLUDE FILE.INCLUDES ARMST.FIELDS, DEPTICK.FIELDS (include files not in extract) | K9: Existing ticket lock is released immediately after read (L89) and edits are written later without a lock — concurrent payment posting (AR.INP.PAYMNTS) can be overwritten; line delete is allowed even after payments were applied to that check; ticket counter can exceed 3 digits and break the 5-digit ID format.
A10: AR.INP.PAYMNTS | B10: AR | C10: Interactive | D10: 1137 | E10: VENDOR | F10: =COUNTIF(Rules!$B$2:$B$1568,A10) -> 33 | G10: =COUNTIFS(Rules!$B$2:$B$1568,A10,Rules!$H$2:$H$1568,"QUESTION") -> 9 | H10: Applies deposit-ticket checks to member open invoices (pay due, pay all, by invoice), with discounts, partial payments, adjustments and vendor credit memos that also post AP credits. | I10: reads APMST, APDIST, APHIST, ARMST, ARINV, DEPTICK, CONTROL ('UPD','APBAT','APPER','MS'), SCREENS · writes ARMST, ARINV, DEPTICK, APDIST, APHIST, APMST, CONTROL | J10: RAWINPUT, MONEY, SUMM, DSP.REPORT, SUBR('-NES'); EXECUTE TERM, SORT DEPTICK; INCLUDE *.FIELDS (not in extract) | K10: Auto-apply (L203-207) pays each invoice's full due even when it exceeds the remaining check (overpay guard commented out); period error message ("2 prior or 1 future") contradicts code (1 prior, up to 2 future); PAYOPT=0 test unreachable; UPD.APDIST sets ERR not EM so a missing-vendor message never shows, then MATWRITEs a blank APMST record; READ.DEPTICK retry loop exits after one wait so DEPTICK may silently not update after ARMST/ARINV were written; MATREADU ARINV ELSE proceeds with empty record (conflates not found/locked); APHIST NET sign opposite to GROSS; YTD.DISC adds 0.
A11: AR.INQ.DEPTICK | B11: AR | C11: Subroutine | D11: 107 | F11: =COUNTIF(Rules!$B$2:$B$1568,A11) -> 2 | G11: =COUNTIFS(Rules!$B$2:$B$1568,A11,Rules!$H$2:$H$1568,"QUESTION") -> 0 | H11: POSH screen-framework hook for the deposit ticket inquiry screen (inquiry only, optional print). | I11: none directly (screen framework via POSH includes; would LIST ARDEPTIC) · writes none | J11: none (EXECUTE of LIST ARDEPTIC is commented out) | K11: Print path is dead; uses a different file name (ARDEPTIC) from the BASIC programs (DEPTICK).
A12: AR.PRT.CRDMEM | B12: AR | C12: Report/print | D12: 167 | E12: VENDOR | F12: =COUNTIF(Rules!$B$2:$B$1568,A12) -> 3 | G12: =COUNTIFS(Rules!$B$2:$B$1568,A12,Rules!$H$2:$H$1568,"QUESTION") -> 0 | H12: Lists member credit memos (ARINV code "CM" splits) for a date range, by member or by vendor, with subtotals. | I12: reads ARMST, APMST, ARINV, CONTROL · writes none | J12: IDATE, P.ASSIGN.SUB, DSP.REPORT; EXECUTE SSELECT ARINV | K12: Only the first CM subvalue per invoice is reported (one CM per invoice is enforced in AR.INP.PAYMNTS); L136 ELSE sets NAME not MNAME so a missing member shows the previous member's name; OPT=1 sorts BY-EXP CODE, not by member.
A13: AR.PRT.EDIINV | B13: AR | C13: Report/print | D13: 83 | E13: VENDOR, PRICING | F13: =COUNTIF(Rules!$B$2:$B$1568,A13) -> 5 | G13: =COUNTIFS(Rules!$B$2:$B$1568,A13,Rules!$H$2:$H$1568,"QUESTION") -> 2 | H13: Prints "Billing for <vendor>" invoices to members for vendor-billed (EDI) shipments held in ARSHIP, using the vendor's own product/description/qty/cost lines. | I13: reads ARSHIP, ARMST, IVMST (opened, unused), CONTROL ('COPY'), APMST · writes none | J13: EXECUTE SSELECT ARSHIP | K13: Prints every ARSHIP record (no selection criteria); IVMST opened but unused; the "3-digit decimals" comment conflicts with dividing cents by 100 (units of VCOST unclear); fixed-form printer escape codes.
A14: AR.RPT.DEPTICK | B14: AR | C14: Report/print | D14: 46 | F14: =COUNTIF(Rules!$B$2:$B$1568,A14) -> 1 | G14: =COUNTIFS(Rules!$B$2:$B$1568,A14,Rules!$H$2:$H$1568,"QUESTION") -> 0 | H14: Detail or summary report of deposit tickets in a ticket-number range (amounts, unapplied, discount adj, CM, adjustments). | I14: reads DEPTICK · writes none | J14: DSP.REPORT; EXECUTE SORT DEPTICK | K14: Ticket IDs are MM+seq so a numeric range spans months oddly; DISC.ADJ dictionary item not in the extracted DEPTICK dict.
A15: AR.SHIP.MNT | B15: Members | C15: Interactive | D15: 436 | F15: =COUNTIF(Rules!$B$2:$B$1568,A15) -> 11 | G15: =COUNTIFS(Rules!$B$2:$B$1568,A15,Rules!$H$2:$H$1568,"QUESTION") -> 2 | H15: Maintains a member's alternate ship-to addresses (SHIPTO records keyed member*code) with UPS zone derived from ZIP. | I15: reads ARMST, SHIPTO, ZIPREF ('UPS', 'STATES', zip records) · writes SHIPTO (write/delete) | J15: EDIT.LINE; EXECUTE SSELECT SHIPTO; INCLUDE ARMST/SHIPTO/ZIPREF.FIELDS (not in extract) | K15: SHIP.ZONE is unreachable (not in the 1-6 correction menu nor the new-entry flow), so manual zone override never runs; L277 deletes ADDRS1 (typo for ADDR1S); L330 missing ";" between ADDR1S and ADDR2S assignments; header says ship-to "later to be added to ARMST" while ARMST already has SHIP.STREET/SHIP.CSZ (attrs 31-32).
A16: AR.TEST.SUB | B16: AR | C16: Utility/maintenance | D16: 38 | F16: =COUNTIF(Rules!$B$2:$B$1568,A16) -> 1 | G16: =COUNTIFS(Rules!$B$2:$B$1568,A16,Rules!$H$2:$H$1568,"QUESTION") -> 0 | H16: One-off diagnostic (GJS 12-27-1999) counting ARINV records that have multiple partial payments. | I16: reads ARINV · writes none | J16: EXECUTE SELECT ARINV | K16: Diagnostic only; no business effect.
A17: AR.UPD.PRO.SUB | B17: AR | C17: Subroutine | D17: 793 | E17: VENDOR | F17: =COUNTIF(Rules!$B$2:$B$1568,A17) -> 13 | G17: =COUNTIFS(Rules!$B$2:$B$1568,A17,Rules!$H$2:$H$1568,"QUESTION") -> 3 | H17: POSH-framework payment-posting screen (called from AR.UPD.DEPTICK) that applies one check to a member's open invoices with full/skip/partial/non-cash codes and writes ARINV/ARMST; an earlier (1999) alternative to AR.INP.PAYMNTS. | I17: reads POSH.WORK ('AR.UPD.PRO.SUB*'port), ARINV, ARMST, APMST · writes ARINV, ARMST, POSH.WORK | J17: POSH.ERROR, POSH.INPUT, MONEY; EXECUTE WHO | K17: Looks unfinished — debug prompt "AT BUILD REC TO WRITE" + INPUT before posting (L685-686); skip test at L339 is always true (NE "" OR NE 2); WORKREC is indexed by display position while posting LOCATEs by invoice number; full-pay reduces balance by the invoice gross although cash = net; MATREADU ELSE STOP conflation is handled with LOCKED clause (ok); DIM AR.MST(34) smaller than ARMST record (47 attrs).
A18: AR1 | B18: Members | C18: Interactive | D18: 124 | F18: =COUNTIF(Rules!$B$2:$B$1568,A18) -> 11 | G18: =COUNTIFS(Rules!$B$2:$B$1568,A18,Rules!$H$2:$H$1568,"QUESTION") -> 5 | H18: Adds new members (auto-numbered) or changes existing member master data (name, address, credit limit, phone, mailings, dues, EIN). | I18: reads CONTROL ('AR'), ARMST, ZIPREF ('UPS','STATES'), STOCK · writes ARMST, STOCK, CONTROL | J18: none | K18: US-only ZIP (AR.SHIP.MNT later allowed Canadian); no lock on CONTROL 'AR' (READV/WRITEV) → duplicate numbers possible; ZIP lookup with Z=0 when prefix below first entry gives empty zone.
A19: AR10 | B19: AR | C19: Batch | D19: 28 | F19: =COUNTIF(Rules!$B$2:$B$1568,A19) -> 3 | G19: =COUNTIFS(Rules!$B$2:$B$1568,A19,Rules!$H$2:$H$1568,"QUESTION") -> 0 | H19: After invoice printing, copies ARSHIP to ARHIST, clears ARSHIP, and deletes billed SCANORD records. | I19: reads ARSHIP, SCANORD · writes ARHIST; clears ARSHIP; deletes SCANORD | J19: EXECUTE COPY FROM ARSHIP TO ARHIST ALL; EXECUTE SELECT SCANORD WITH BILL.DATE | K19: COPY without OVERWRITING silently skips keys already in ARHIST, then ARSHIP is cleared anyway — potential history loss; no check that the copy succeeded.
A20: AR11 | B20: AR | C20: Utility/maintenance | D20: 26 | F20: =COUNTIF(Rules!$B$2:$B$1568,A20) -> 1 | G20: =COUNTIFS(Rules!$B$2:$B$1568,A20,Rules!$H$2:$H$1568,"QUESTION") -> 0 | H20: Recomputes ARMST aging buckets and balance from ARINV open invoices (marked "DON'T USE"). | I20: reads ARINV, ARMST · writes ARMST | J20: none | K20: Header "$$%% DON'T USE" (L2 is not valid BASIC); 300-invoice cap; no locks.
A21: AR12 | B21: AR | C21: Batch | D21: 67 | E21: VENDOR, PRODUCT | F21: =COUNTIF(Rules!$B$2:$B$1568,A21) -> 6 | G21: =COUNTIFS(Rules!$B$2:$B$1568,A21,Rules!$H$2:$H$1568,"QUESTION") -> 2 | H21: Year-end roll: moves YTD figures to prior year and zeroes YTD counters on STOCK, IVMST, VNMST, ARMST; clears IVSOLD and IVEND. | I21: reads STOCK, IVMST, VNMST, ARMST · writes STOCK, IVMST, VNMST, ARMST; clears IVSOLD, IVEND | J21: none | K21: Prior-year fields stored in dollars while YTD in cents (unit inconsistency); 11-26-01 note says ARMST attr 22 no longer holds shares but share calc removed; AR.ADJ.CY sets HI.CRED from PY.HI.CRED instead — two different year-end rules; MATREADU ELSE skips locked records silently.
A22: AR13 | B22: Members | C22: Report/print | D22: 33 | F22: =COUNTIF(Rules!$B$2:$B$1568,A22) -> 4 | G22: =COUNTIFS(Rules!$B$2:$B$1568,A22,Rules!$H$2:$H$1568,"QUESTION") -> 2 | H22: Prints annual member stock (patronage share) letters (1986). | I22: reads ARMST, STOCK · writes none | J22: none | K22: "19":YEAR Y2K bug; STOCK attr 3 meaning conflicts with dict (PATR.BAL).
A23: AR14 | B23: Members | C23: Utility/maintenance | D23: 18 | F23: =COUNTIF(Rules!$B$2:$B$1568,A23) -> 1 | G23: =COUNTIFS(Rules!$B$2:$B$1568,A23,Rules!$H$2:$H$1568,"QUESTION") -> 1 | H23: Sequentially numbers ARMST/ARMST2 field 28, 29, 33, 34 or 35 from an active select list. | I23: reads (select list) · writes operator-named file (ARMST or ARMST2) | J23: none | K23: Prompt lists 28/29/33/34 but also accepts 35 (PROMASTER) — would overwrite PROMASTER flag with a sequence number.
A24: AR15 | B24: Members | C24: Utility/maintenance | D24: 13 | F24: =COUNTIF(Rules!$B$2:$B$1568,A24) -> 1 | G24: =COUNTIFS(Rules!$B$2:$B$1568,A24,Rules!$H$2:$H$1568,"QUESTION") -> 1 | H24: Calculator for member share buyout to cap holdings at a percentage of total shares. | I24: none | J24: none | K24: Must edit code to change the percentage; header says 5% but live code uses 20%.
A25: AR16 | B25: Members | C25: Interactive | D25: 34 | F25: =COUNTIF(Rules!$B$2:$B$1568,A25) -> 2 | G25: =COUNTIFS(Rules!$B$2:$B$1568,A25,Rules!$H$2:$H$1568,"QUESTION") -> 1 | H25: Toggles a member's credit-hold status. | I25: reads ARMST · writes ARMST | J25: none | K25: Mixed money units on one screen; no audit of who placed the hold.
A26: AR17 | B26: Vendors | C26: Utility/maintenance | D26: 27 | E26: VENDOR | F26: =COUNTIF(Rules!$B$2:$B$1568,A26) -> 1 | G26: =COUNTIFS(Rules!$B$2:$B$1568,A26,Rules!$H$2:$H$1568,"QUESTION") -> 1 | H26: Fills IVEND attrs 4/5 with each member's combined amount and surcharge for vendors 195 and 279. | I26: reads IVEND · writes IVEND | J26: none | K26: LOCATE BY 'AR' assumes IVEND attr 1 vendor list sorted; unlocked MATREAD then MATWRITE; OPEN failure doesn't stop.
A27: AR18 | B27: Members | C27: Interactive | D27: 55 | E27: VENDOR | F27: =COUNTIF(Rules!$B$2:$B$1568,A27) -> 4 | G27: =COUNTIFS(Rules!$B$2:$B$1568,A27,Rules!$H$2:$H$1568,"QUESTION") -> 1 | H27: Credits members with extra surcharge income and gross purchases from direct-billing vendors (manual entry per vendor/member). | I27: reads APMST, ARMST, BVEND · writes ARMST, BVEND | J27: none | K27: Cents-without-decimal entry differs from programs using MONEY; no audit trail of who entered what.
A28: AR19 | B28: Members | C28: Interactive | D28: 128 | E28: VENDOR, PO | F28: =COUNTIF(Rules!$B$2:$B$1568,A28) -> 6 | G28: =COUNTIFS(Rules!$B$2:$B$1568,A28,Rules!$H$2:$H$1568,"QUESTION") -> 0 | H28: Enters/edits member open direct-vendor POs (VENDORD) that count against the member's credit exposure. | I28: reads ARMST, APMST, VENDORD · writes VENDORD | J28: MONEY | K28: A "change" reached via the L44-54 loop keeps ADD=1 and inserts a duplicate instead of updating; YN can be stale in that loop; BILLED (attr 5) is never set here.
A29: AR1A | B29: Members | C29: Interactive | D29: 120 | F29: =COUNTIF(Rules!$B$2:$B$1568,A29) -> 4 | G29: =COUNTIFS(Rules!$B$2:$B$1568,A29,Rules!$H$2:$H$1568,"QUESTION") -> 2 | H29: Copy of AR1 for adding/changing IPI (non-PRO) members; only differences listed. | I29: reads CONTROL ('AR2'), ARMST, ZIPREF · writes ARMST, CONTROL | J29: none | K29: Duplicates AR1 logic; "IPI" not defined anywhere in code; attr 23 overloaded (mailings prompt vs member type).
A30: AR1B | B30: Members | C30: Interactive | D30: 137 | F30: =COUNTIF(Rules!$B$2:$B$1568,A30) -> 6 | G30: =COUNTIFS(Rules!$B$2:$B$1568,A30,Rules!$H$2:$H$1568,"QUESTION") -> 3 | H30: Copy of AR1A (05-26-11) for adding/changing Canadian affiliate members; only differences listed. | I30: reads CONTROL ('AR2'), ARMST, ZIPREF ('PROVINCE') · writes ARMST, CONTROL | J30: none | K30: Message says "PRO or AFF" for type 2 while AR1A calls type 2 IPI — naming of member types inconsistent.
A31: AR2 | B31: AR | C31: Report/print | D31: 71 | E31: VENDOR, PRICING | F31: =COUNTIF(Rules!$B$2:$B$1568,A31) -> 5 | G31: =COUNTIFS(Rules!$B$2:$B$1568,A31,Rules!$H$2:$H$1568,"QUESTION") -> 1 | H31: Prints member invoices from ARSHIP (1994 version): PRO product lines, or a single "Billing for <vendor>" line for direct-bill vendor charges with a terms-dispute notice. | I31: reads ARSHIP, ARMST, IVMST, CONTROL ('COPY'), APMST · writes none | J31: none (relies on active select list) | K31: 200-line cap; unit price derived by division (may round); superseded in part by AR.PRT.EDIINV and AR5 variants.
A32: AR20 | B32: Members | C32: Interactive | D32: 36 | F32: =COUNTIF(Rules!$B$2:$B$1568,A32) -> 2 | G32: =COUNTIFS(Rules!$B$2:$B$1568,A32,Rules!$H$2:$H$1568,"QUESTION") -> 1 | H32: Adds/changes a member's permanent ship-to address on ARMST and resets the UPS zone from the ship-to ZIP. | I32: reads ARMST, ZIPREF ('UPS','STATES') · writes ARMST | J32: none | K32: Zone overwrite drops the air-zone suffix that AR1 maintains in attr 25; US ZIP only; LOCATE 'AL' assumes STATES sorted while AR1 uses unsorted LOCATE.
A33: AR21 | B33: Members | C33: Utility/maintenance | D33: 17 | E33: VENDOR | F33: =COUNTIF(Rules!$B$2:$B$1568,A33) -> 1 | G33: =COUNTIFS(Rules!$B$2:$B$1568,A33,Rules!$H$2:$H$1568,"QUESTION") -> 0 | H33: One-off 1995 conversion setting ARMST prior-year sales from old ARMST2 YTD plus BVEND2 direct-bill amounts. | I33: reads ARMST2, BVEND2 · writes ARMST | J33: none | K33: Second term is not truncated to whole dollars (fractional dollars added to a whole-dollar field); READVU lock then WRITEV.
A34: AR3 | B34: AR | C34: Interactive | D34: 285 | F34: =COUNTIF(Rules!$B$2:$B$1568,A34) -> 16 | G34: =COUNTIFS(Rules!$B$2:$B$1568,A34,Rules!$H$2:$H$1568,"QUESTION") -> 6 | H34: Original member payment entry (no deposit ticket): pays due/all/selected invoices with prompt-pay discount, records credits, updates ARMST/ARINV and stamps date paid on ARHIST. | I34: reads ARMST, ARINV, ARHIST, CONTROL ('UPD','INV','MS') · writes ARMST, ARINV, ARHIST (attr 16), CONTROL ('INV','MS') | J34: MONEY; UPD.ARLOG (commented out); EXECUTE SELECT ARHIST | K34: LOCKED clauses at L243 and L260 set NOT.LOCKED = 1, so lock waits never happen; credit path (L251-254) calls the payment routine with stale B() values from the last invoice viewed; credit invoice written with no amount (attr 3) — only AMTPAID; open-error label for ARHIST says ARMST; ARLOG audit commented out; discount rules differ between options.
A35: AR4 | B35: AR | C35: Batch | D35: 76 | E35: PRODUCT | F35: =COUNTIF(Rules!$B$2:$B$1568,A35) -> 8 | G35: =COUNTIFS(Rules!$B$2:$B$1568,A35,Rules!$H$2:$H$1568,"QUESTION") -> 2 | H35: Month-end AR close: purges fully paid invoices, ages open invoices, assesses 1.5% service charges, rolls ARMST aging buckets and advances the AR month. | I35: reads CONTROL ('UPD'), ARMST, ARINV, DICT IVMST (opened, write commented out) · writes ARMST, ARINV, ARSHIP, CONTROL | J35: none | K35: Header says service charge "at 30, not 60 days" but CURRENT is included in the base; SID "date − 9000 to retain 4 digits" now yields 5 digits (dates > 19000) and can collide across years; if ARINV is missing the ARMST lock is released then the record is still written; DICT IVMST opened but unused; fractions dropped by INT not rounded.
A36: AR5 | B36: AR | C36: Report/print | D36: 107 | F36: =COUNTIF(Rules!$B$2:$B$1568,A36) -> 7 | G36: =COUNTIFS(Rules!$B$2:$B$1568,A36,Rules!$H$2:$H$1568,"QUESTION") -> 0 | H36: Prints monthly member statements (three-part pre-printed form) with prompt-pay discount and past-due flags, and advances the month-end state. | I36: reads CONTROL ('UPD'), ARINV, ARMST · writes ERROR (missing records), CONTROL ('UPD' attr 1 = 4) | J36: none (relies on active select list) | K36: Missing ARINV/ARMST are logged to ERROR and the run ABORTs at end; READVU on 'UPD' held for whole run; discount column shows terms % even when past due.
A37: AR5.LASER | B37: AR | C37: Test-variant | D37: 151 | E37: VENDOR | F37: =COUNTIF(Rules!$B$2:$B$1568,A37) -> 3 | G37: =COUNTIFS(Rules!$B$2:$B$1568,A37,Rules!$H$2:$H$1568,"QUESTION") -> 0 | H37: Laser-printer (PCL) version of AR5 statements that also shows the vendor invoice number and vendor name per line; only differences from AR5 listed. | I37: reads APMST, ARMST, ARINV, ARHIST, ARHIST.98, CONTROL · writes ERROR, CONTROL | J37: none | K37: Hard-coded archive file name ARHIST.98 (1998 history) — later years' archived invoices not found; PCL escape strings hard-coded.
A38: AR5.LASER.INTERIM | B38: AR | C38: Test-variant | D38: 152 | E38: VENDOR | F38: =COUNTIF(Rules!$B$2:$B$1568,A38) -> 3 | G38: =COUNTIFS(Rules!$B$2:$B$1568,A38,Rules!$H$2:$H$1568,"QUESTION") -> 2 | H38: Mid-month ("interim") variant of AR5.LASER; only differences listed. | I38: reads APMST, ARMST, ARINV, ARHIST, ARHIST.00, CONTROL · writes ERROR, CONTROL | J38: none | K38: Still writes CONTROL 'UPD' = 4 when UPD = 3 even though it is an interim run (inherited L-149 logic); hard-coded archive year.
A39: AR5.OFFICE | B39: AR | C39: Test-variant | D39: 154 | F39: =COUNTIF(Rules!$B$2:$B$1568,A39) -> 1 | G39: =COUNTIFS(Rules!$B$2:$B$1568,A39,Rules!$H$2:$H$1568,"QUESTION") -> 0 | H39: Office-copy variant of AR5.LASER; only differences listed. | I39: reads APMST, ARMST, ARINV, ARHIST, ARHIST.98, CONTROL · writes ERROR, CONTROL | J39: none | K39: Reads ARHIST/APMST per line for nothing; same UPD=4 side effect as AR5.
A40: AR6 | B40: Reporting | C40: Utility/maintenance | D40: 21 | E40: VENDOR | F40: =COUNTIF(Rules!$B$2:$B$1568,A40) -> 1 | G40: =COUNTIFS(Rules!$B$2:$B$1568,A40,Rules!$H$2:$H$1568,"QUESTION") -> 0 | H40: Rescales the ARMST "GRAPH" dictionary item (member sales bar graph) to the current largest member's sales. | I40: reads ARMST, BVEND · writes DICT ARMST 'GRAPH' | J40: EXECUTE CD ARMST GRAPH | K40: Program rewrites a dictionary at runtime; aborts if any ARMST lacks attr 9.
A41: AR7 | B41: AR | C41: Interactive | D41: 398 | E41: VENDOR, PO, PRICING | F41: =COUNTIF(Rules!$B$2:$B$1568,A41) -> 28 | G41: =COUNTIFS(Rules!$B$2:$B$1568,A41,Rules!$H$2:$H$1568,"QUESTION") -> 12 | H41: Direct-vendor ("non-PRO MDs") billing: for each vendor invoice shipped direct to a member, bills the member (plus PRO surcharge) on a new PRO invoice and optionally posts the vendor invoice to AP. | I41: reads CONTROL ('UPD','APBAT','APPER','INV','MS'), ARMST, APMST, VNIDX, VNMST, VENDORD, APHIST, IVEND, ARINV · writes ARMST, APMST, VNMST, VENDORD, IVEND, ARINV, ARSHIP, APDIST, APHIST, CONTROL | J41: !SLEEP$ | K41: Dollar-amount discount (>20) sets NET correctly but APDIST DISC is still computed as a percent (L344); VNMST LOCKED clause sleeps then updates a record it never read (L133-137); invoice counter wraps at 99999 here but 999999 in AR3; APMST/VNMST attrs 30/31/13 used for purposes that contradict dict names; APMST locked for the whole vendor session; NET undefined when AP=N but not used.
A42: AR8 | B42: Members | C42: Batch | D42: 119 | E42: PRODUCT | F42: =COUNTIF(Rules!$B$2:$B$1568,A42) -> 11 | G42: =COUNTIFS(Rules!$B$2:$B$1568,A42,Rules!$H$2:$H$1568,"QUESTION") -> 4 | H42: Monthly dues billing for PRO and Affiliate members: creates a dues invoice per member (product 9995) and, for FotoSource-type members, an FSINV spreadsheet line and email. | I42: reads CONTROL ('UPD','MON','FSINV.FIELDS','FSINV.EMAIL.PARAMS','INV','MS'), ARMST, ARINV · writes IVMST (9995 desc), ARMST, ARINV, ARSHIP, FSINV, CONTROL | J42: IV.UPD.FSINV.XLS, EMAIL.FSINV; UPD.ARLOG (commented out) | K42: Member type 3 is "Canadian affiliate" in AR1B but treated as FotoSource here; L61 converts the wrong variable (DUES); dues entered without decimal ("50") billed as $0.50; MATREADU ELSE skips locked members silently; ARLOG commented out.
A43: AR9 | B43: Reporting | C43: Report/print | D43: 29 | F43: =COUNTIF(Rules!$B$2:$B$1568,A43) -> 2 | G43: =COUNTIFS(Rules!$B$2:$B$1568,A43,Rules!$H$2:$H$1568,"QUESTION") -> 0 | H43: Prints the monthly totals report from CONTROL 'MS' and, if statements are done, resets the month cycle. | I43: reads CONTROL ('MS','UPD') · writes CONTROL | J43: none | K43: MS updated by many programs without consistent attribute meaning (AR.INP.PAYMNTS and AR3 add payments to attr 4; AR7 adds billing to 3); "CAPITOL" typo.
A44: AR9.BU | B44: Reporting | C44: Test-variant | D44: 29 | F44: =COUNTIF(Rules!$B$2:$B$1568,A44) -> 1 | G44: =COUNTIFS(Rules!$B$2:$B$1568,A44,Rules!$H$2:$H$1568,"QUESTION") -> 0 | H44: Copy of AR9 run against CONTROL.BU; only differences listed. | I44: reads CONTROL.BU · writes CONTROL.BU | J44: none | K44: Backup copy; would reset CONTROL.BU cycle state.
A45: ARHIST.CHANGE | B45: AR | C45: Utility/maintenance | D45: 9 | F45: =COUNTIF(Rules!$B$2:$B$1568,A45) -> 1 | G45: =COUNTIFS(Rules!$B$2:$B$1568,A45,Rules!$H$2:$H$1568,"QUESTION") -> 1 | H45: One-off script moving member 7063's 2009 history (ARHIST.09) to member 3417. | I45: reads ARHIST.09 · writes ARHIST.09 | J45: EXECUTE SELECT ARHIST.09 | K45: Overwrites any existing target record; no locking.
A46: AUTO.ORDER | B46: Orders | C46: Staging-processor | D46: 172 | E46: VENDOR, PRODUCT, PO, PRICING | F46: =COUNTIF(Rules!$B$2:$B$1568,A46) -> 11 | G46: =COUNTIFS(Rules!$B$2:$B$1568,A46,Rules!$H$2:$H$1568,"QUESTION") -> 5 | H46: Creates member orders (IVORD/ORDHIST) and vendor order lines (VNORD) from TEAMPRO staging records (one record per member: PO, instructions, discount, future date, then product/qty pairs), then prints vendor orders. | I46: reads TEAMPRO, ARMST, IVMST, CONTROL ('UPD','ORD'), ZIPREF · writes IVORD, ORDHIST, VNORD, IVMST, ARMST, CONTROL; deletes TEAMPRO | J46: EXECUTE PR1, RUN IV10 (via SSELECT VNORD ... DATA) | K46: "No vendor" check compares IVMST vendor to VEND<1,POS> before it is appended, so it only fires when the product has no vendor and the message is misleading; ORDER(10)<1,2> TQTY never set; missing IVMST product CHAIN ABORTs mid-run leaving earlier orders created and TEAMPRO partially processed; ZIPREF zones read but unused; locks left on IVMST between WRITEVU and WRITEV.
A47: BLD.IVMST.PW | B47: Products | C47: Outbound-generator | D47: 44 | E47: PRODUCT, PRICING | F47: =COUNTIF(Rules!$B$2:$B$1568,A47) -> 4 | G47: =COUNTIFS(Rules!$B$2:$B$1568,A47,Rules!$H$2:$H$1568,"QUESTION") -> 1 | H47: Builds a tab-delimited product price list (product, description, member price, multiple, status, UPC) for Photoware users into PWDB record 'IVMST.PW'. | I47: reads IVMST, CONTROL (opened) · writes PWDB ('IVMST.PW') | J47: none (EXECUTE SEND_PWDB commented out); INCLUDE IVMST.FIELDS | K47: Price unit (cents) differs from BLD.IVMST.XML (dollars) for the same feed; surcharge formula differs from AUTO.ORDER's string-concatenated multiplier for single-digit or 3-digit PCT values.
A48: BLD.IVMST.XML | B48: Products | C48: Outbound-generator | D48: 46 | E48: PRODUCT, PRICING | F48: =COUNTIF(Rules!$B$2:$B$1568,A48) -> 2 | G48: =COUNTIFS(Rules!$B$2:$B$1568,A48,Rules!$H$2:$H$1568,"QUESTION") -> 0 | H48: Earlier XML version of the Photoware product/price feed into PWDB 'IVMST.XML'. | I48: reads IVMST, CONTROL ('XML.HEADER') · writes PWDB ('IVMST.XML'), CONTROL (default XML header if missing) | J48: none (SEND_PWDB commented out) | K48: Superseded 07-02-08 by BLD.IVMST.PW; literal "- " prefixes before tags make the XML invalid.
A49: BLD.IVPO | B49: Inventory | C49: Utility/maintenance | D49: 33 | E49: VENDOR, PRODUCT, PO | F49: =COUNTIF(Rules!$B$2:$B$1568,A49) -> 4 | G49: =COUNTIFS(Rules!$B$2:$B$1568,A49,Rules!$H$2:$H$1568,"QUESTION") -> 2 | H49: One-off (2003) conversion that builds IVPO purchase-order records from the PO multivalues stored on IVMST products. | I49: reads IVMST · writes IVPO, IVMST | J49: EXECUTE SSELECT IVMST BY-EXP PO.NUM | K49: Not idempotent (re-run appends duplicate lines and re-adds totals); a PO's vendor is taken from whichever product sorts first; "Y" cost suffix meaning undocumented.
A50: BLD.IVSOLD | B50: Reporting | C50: Utility/maintenance | D50: 70 | E50: PRODUCT | F50: =COUNTIF(Rules!$B$2:$B$1568,A50) -> 3 | G50: =COUNTIFS(Rules!$B$2:$B$1568,A50,Rules!$H$2:$H$1568,"QUESTION") -> 1 | H50: Rebuilds IVSOLD (per member: products and quantities bought this year) from ARHIST for chosen members or all ("*"). | I50: reads ARMST, ARHIST · writes IVSOLD | J50: EXECUTE SSELECT ARHIST | K50: Lock-wait loop never waits (no LOCKED clause); member taken from key chars 1-4 (assumes 4-digit members).
A51: BLD.QS | B51: Reporting | C51: Utility/maintenance | D51: 52 | E51: PRODUCT | F51: =COUNTIF(Rules!$B$2:$B$1568,A51) -> 1 | G51: =COUNTIFS(Rules!$B$2:$B$1568,A51,Rules!$H$2:$H$1568,"QUESTION") -> 0 | H51: One-off (08-23-10) reconciliation that builds a per-member QSTEMP record comparing quantities shipped by product from SCANORD, ARHIST and IVSOLD. | I51: reads SCANORD, ARHIST, IVSOLD · writes QSTEMP | J51: EXECUTE SELECT SCANORD/ARHIST/IVSOLD | K51: Hard-coded 2010 dates; IV.QS column (4) not initialised on insert.
A52: BLD.SCANORD.UPS | B52: Orders | C52: Staging-processor | D52: 137 | F52: =COUNTIF(Rules!$B$2:$B$1568,A52) -> 5 | G52: =COUNTIFS(Rules!$B$2:$B$1568,A52,Rules!$H$2:$H$1568,"QUESTION") -> 0 | H52: Loads UPS shipping export CSV content (UPS.PERM records keyed EXP...) onto SCANORD pick/ship records: tracking numbers, package counts, published and negotiated freight cost. | I52: reads UPS.PERM, SCANORD · writes SCANORD | J52: EXECUTE SSELECT UPS.PERM IDLIKE EXP..., SSELECT SCANORD WITH PACKAGES > "1"; INCLUDE SCANORD.FIELDS | K52: Header note "only update if neg.cost different" is not implemented; REMOVE.EXTRA.INFO falls through into SET.VALS.TO.NULL when only one tracking #; error text says "PURGE.UPS"; uses both SCANORD.PKGS and SCANORD.PACKAGES names (include not in extract).
A53: BUILD.IVCAT | B53: Products | C53: Utility/maintenance | D53: 24 | E53: PRODUCT | F53: =COUNTIF(Rules!$B$2:$B$1568,A53) -> 2 | G53: =COUNTIFS(Rules!$B$2:$B$1568,A53,Rules!$H$2:$H$1568,"QUESTION") -> 1 | H53: Builds the IVCAT UPC→product cross-reference by generating a PRO UPC for every IVMST product (2002). | I53: reads IVMST · writes IVCAT | J53: none | K53: Generates PRO UPCs for all products including vendor-branded ones (BUILD.UPC later restricted this); product numbers longer than 4 digits produce over-length UPCs; check digit only uses 11 positions.
A54: BUILD.PROMASTER | B54: Members | C54: Utility/maintenance | D54: 35 | E54: PRODUCT | F54: =COUNTIF(Rules!$B$2:$B$1568,A54) -> 5 | G54: =COUNTIFS(Rules!$B$2:$B$1568,A54,Rules!$H$2:$H$1568,"QUESTION") -> 4 | H54: Computes each member's PROMASTER-brand purchases from ARHIST (2002 onward) into ARMST attr 35 PROMASTER. | I54: reads ARHIST, IVMST, ARMST · writes ARMST (attr 35) | J54: EXECUTE SSELECT ARHIST WITH DATE > "12.31.01" AND WITH GRP > 0 | K54: Without a member ≥ 9990 in the list the end-of-list path loops forever (GO 40 → GO 10 re-reads the last ID); credits treated differently between group sets; groups 16, 18 and ≥ 20 silently excluded.
A55: BUILD.PROMASTER.2 | B55: Members | C55: Test-variant | D55: 35 | E55: PRODUCT | F55: =COUNTIF(Rules!$B$2:$B$1568,A55) -> 1 | G55: =COUNTIFS(Rules!$B$2:$B$1568,A55,Rules!$H$2:$H$1568,"QUESTION") -> 0 | H55: Copy of BUILD.PROMASTER run against ARMST2 / ARHIST.01 / IVMST2 (2001 archive files); only differences listed. | I55: reads ARHIST.01, IVMST2 · writes ARMST2 | J55: EXECUTE SSELECT ARHIST.01 WITH GRP > 0 | K55: Same infinite-loop risk as BUILD.PROMASTER.
A56: BUILD.UPC | B56: Products | C56: Utility/maintenance | D56: 28 | E56: VENDOR, PRODUCT | F56: =COUNTIF(Rules!$B$2:$B$1568,A56) -> 3 | G56: =COUNTIFS(Rules!$B$2:$B$1568,A56,Rules!$H$2:$H$1568,"QUESTION") -> 2 | H56: Assigns PRO-prefix UPCs to IVMST products that have none and records them in IVCAT (02-21-02). | I56: reads IVMST · writes IVMST (attr 29 UPC), IVCAT | J56: EXECUTE SELECT IVMST WITH NO UPC | K56: Products from vendors other than 992 with no UPC also get a PRO UPC (only 992 is filtered); over-length UPCs for 5+ digit products.
A57: BUILD.YTD.SALES | B57: Reporting | C57: Utility/maintenance | D57: 38 | E57: PRODUCT | F57: =COUNTIF(Rules!$B$2:$B$1568,A57) -> 1 | G57: =COUNTIFS(Rules!$B$2:$B$1568,A57,Rules!$H$2:$H$1568,"QUESTION") -> 0 | H57: Builds SALES.TEMP per product (total qty sold, number of members, description, group, E-group) from the 2005 IVSOLD archive. | I57: reads IVSOLD.05, IVMST · writes SALES.TEMP (cleared first) | J57: none | K57: Hard-coded archive file IVSOLD.05 despite "ytd" name.
A58: CAPTURE | B58: Utility | C58: Utility/maintenance | D58: 59 | F58: =COUNTIF(Rules!$B$2:$B$1568,A58) -> 1 | G58: =COUNTIFS(Rules!$B$2:$B$1568,A58,Rules!$H$2:$H$1568,"QUESTION") -> 0 | H58: Runs any LIST/SORT sentence and transfers the captured report to a PC file (default C:\DOWNLOADS\) via the FT file-transfer utility. | I58: writes BP (temporary TMP_<user>.RPT, then deleted) | J58: EXECUTE TERM, PTERM, GET-LIST, FT; INCLUDE UTLBP I_GETPORT | K58: Stray quote at L53 (`TXT.ID'`); writes temp data into the program file BP.
A59: CASE.CTN | B59: Products | C59: Interactive | D59: 13 | E59: PRODUCT | F59: =COUNTIF(Rules!$B$2:$B$1568,A59) -> 1 | G59: =COUNTIFS(Rules!$B$2:$B$1568,A59,Rules!$H$2:$H$1568,"QUESTION") -> 0 | H59: Manually maintains a product's case and carton pack quantities. | I59: reads IVMST · writes IVMST | J59: none | K59: Exit test ID[1,3]='E' only matches exactly "E"; blank entry wipes existing values; non-numeric accepted.
A60: CHANGE | B60: Members | C60: Utility/maintenance | D60: 8 | F60: =COUNTIF(Rules!$B$2:$B$1568,A60) -> 1 | G60: =COUNTIFS(Rules!$B$2:$B$1568,A60,Rules!$H$2:$H$1568,"QUESTION") -> 0 | H60: One-off copy of ARMST2 attr 29 into ARMST attr 29 for a select list. | I60: reads ARMST2 · writes ARMST | J60: none | K60: Unlocked WRITEV; blanks attr 29 when ARMST2 missing.
A61: CHANGE.INST | B61: Orders | C61: Interactive | D61: 119 | E61: PO | F61: =COUNTIF(Rules!$B$2:$B$1568,A61) -> 5 | G61: =COUNTIFS(Rules!$B$2:$B$1568,A61,Rules!$H$2:$H$1568,"QUESTION") -> 1 | H61: Changes the special instructions on a PRO order (ORDHIST, IVORD and all its vendor orders) if the order has not been started. | I61: reads ORDHIST, ARMST, VNORD · writes VNORD (attr 7), ORDHIST (attr 9), IVORD (attr 9) | J61: EDIT.LINE; EXECUTE SELECT VNORD WITH ORDER | K61: Blank line 1 means no update (instructions cannot be cleared); open-error text says "BP IV3"; dated-order status encoded in free-text instructions.
A62: CHANGE.VNORD | B62: Orders | C62: Utility/maintenance | D62: 60 | E62: VENDOR, PRODUCT, PO | F62: =COUNTIF(Rules!$B$2:$B$1568,A62) -> 5 | G62: =COUNTIFS(Rules!$B$2:$B$1568,A62,Rules!$H$2:$H$1568,"QUESTION") -> 3 | H62: After a product's vendor changes, moves that product's open vendor-order lines from the old vendor's VNORD records to the new vendor's and updates NUMBER records. | I62: reads IVMST, VNMST, VNORD, NUMBER · writes VNORD, NUMBER | J62: EXECUTE SELECT VNORD, SELECT NUMBER | K62: Write to the new vendor runs even when the old record was locked/missing or the product wasn't found, re-using the previous line (duplicate lines possible); fixed 3-char vendor prefix breaks for 4-digit vendors; old vendor validated against VNMST while key uses IVMST vendor.
A63: CHG.DATING | B63: Orders | C63: Utility/maintenance | D63: 31 | E63: PO | F63: =COUNTIF(Rules!$B$2:$B$1568,A63) -> 2 | G63: =COUNTIFS(Rules!$B$2:$B$1568,A63,Rules!$H$2:$H$1568,"QUESTION") -> 2 | H63: Marks an order as 1st dated, 2nd dated, or not dated by overwriting its special-instructions field. | I63: reads IVORD, ARMST · writes IVORD (attr 9), ORDHIST (attr 9), VNORD (attr 7) | J63: EXECUTE SELECT VNORD WITH ORDER | K63: Destroys existing special instructions; no locks; dated-order business meaning (billing/terms timing) not defined in code.
A64: CHK.ARMST.NAME | B64: Members | C64: Report/print | D64: 46 | F64: =COUNTIF(Rules!$B$2:$B$1568,A64) -> 1 | G64: =COUNTIFS(Rules!$B$2:$B$1568,A64,Rules!$H$2:$H$1568,"QUESTION") -> 0 | H64: Reports ARMST records with duplicate member names (adjacent in name sort) to the printer and ARERR. | I64: reads ARMST · writes ARERR | J64: EXECUTE DHPRT, SSELECT ARMST BY NAME | K64: Exact-match only (case/spacing variants missed).
A65: CHK.CAN.TOTS | B65: AR | C65: Batch | D65: 25 | F65: =COUNTIF(Rules!$B$2:$B$1568,A65) -> 1 | G65: =COUNTIFS(Rules!$B$2:$B$1568,A65,Rules!$H$2:$H$1568,"QUESTION") -> 1 | H65: Pre-month-end check (04-26-12) that aborts if Canadian members have any balances. | I65: reads ARMST · writes VOC ('SJL-RESULT') | J65: EXECUTE SUM ARMST WITH TYPE = "CAN" | K65: Inner loop reuses L; `OPEN 'VOC' THEN` / `WRITE ... ON 'SJL-RESULT'` lack a file variable; why Canadian members must carry zero balances before month-end is not explained.
A66: CLEAN.UP.MV | B66: AR | C66: Utility/maintenance | D66: 16 | F66: =COUNTIF(Rules!$B$2:$B$1568,A66) -> 1 | G66: =COUNTIFS(Rules!$B$2:$B$1568,A66,Rules!$H$2:$H$1568,"QUESTION") -> 0 | H66: One-off (2000) fix deleting the last product/qty/amount value on ARHIST.95 records (trailing empty multivalue). | I66: reads ARHIST.95 · writes ARHIST.95 | J66: none (needs select list) | K66: Deletes real data if the trailing value is not empty.
A67: COMPARE.QS | B67: Reporting | C67: Utility/maintenance | D67: 32 | E67: PRODUCT | F67: =COUNTIF(Rules!$B$2:$B$1568,A67) -> 1 | G67: =COUNTIFS(Rules!$B$2:$B$1568,A67,Rules!$H$2:$H$1568,"QUESTION") -> 0 | H67: One-off (08-23-10) display of products in QSTEMP not present in a member's IVSOLD. | I67: reads QSTEMP, IVSOLD · writes none | J67: none | K67: Uses QSTEMP attr 2/3 as qty although BLD.QS stores SCANORD qty in 2 and ARHIST qty in 3.
A68: CONV.ARHIST | B68: AR | C68: Utility/maintenance | D68: 26 | F68: =COUNTIF(Rules!$B$2:$B$1568,A68) -> 1 | G68: =COUNTIFS(Rules!$B$2:$B$1568,A68,Rules!$H$2:$H$1568,"QUESTION") -> 0 | H68: One-off (10-29-02) renumbering of a series of invoices (+50) in ARHIST keys and ARINV. | I68: reads ARHIST, ARINV · writes ARHIST, ARINV | J68: EXECUTE SELECT ARHIST WITH NUMBER GE "100201" | K68: Not idempotent; target ARHIST key overwritten if it exists; ARINV LOCATE on invoice number only attr 1.
A69: CONVERT.DATED | B69: Orders | C69: Interactive | D69: 41 | E69: PO | F69: =COUNTIF(Rules!$B$2:$B$1568,A69) -> 2 | G69: =COUNTIFS(Rules!$B$2:$B$1568,A69,Rules!$H$2:$H$1568,"QUESTION") -> 1 | H69: Converts a not-yet-started order to a 1st or 2nd dated order (2007). | I69: reads ORDHIST, ARMST, VNORD · writes VNORD (attr 7), ORDHIST (attr 9), IVORD (attr 9) | J69: EXECUTE SELECT VNORD WITH ORDER | K69: Duplicates CHG.DATING/CHANGE.INST logic; READVU locks taken in the check loop are not released before "GO 5"; existing special instructions lost.
A70: CONVERT.FSINVS | B70: AR | C70: Utility/maintenance | D70: 86 | F70: =COUNTIF(Rules!$B$2:$B$1568,A70) -> 3 | G70: =COUNTIFS(Rules!$B$2:$B$1568,A70,Rules!$H$2:$H$1568,"QUESTION") -> 3 | H70: Moves all open invoices of FotoSource members (ARMST TYPE = "CAN") onto the FotoSource master account 7000 (06-23-11). | I70: reads ARMST, ARINV · writes ARMST, ARINV (deletes member ARINV) | J70: EXECUTE SELECT ARMST WITH TYPE = "CAN" | K70: Uses gross AMOUNT not open amount (AMOUNT − AMTPAID); only NEW.MON bucket moved, other aging buckets left on members; trimming at L48 chops the last character of the master's existing data when it isn't empty; master written only at the end, so an ABORT mid-run loses deleted member invoices.
A71: CONVERT.TERMS | B71: Orders | C71: Interactive | D71: 62 | E71: PO, PRICING | F71: =COUNTIF(Rules!$B$2:$B$1568,A71) -> 3 | G71: =COUNTIFS(Rules!$B$2:$B$1568,A71,Rules!$H$2:$H$1568,"QUESTION") -> 1 | H71: Changes the terms value (attr 11) on an unbilled, active PRO order (03-09-11). | I71: reads ORDHIST, IVORD, ARMST (VNORD opened, unused) · writes ORDHIST (attr 11), IVORD (attr 11) | J71: none | K71: Lock owner taken from SYSTEM(0) instead of STATUS(); billed-date loop never ends if attr 14 holds only value marks; terms not propagated to VNORD.
A72: COPY.UPC | B72: Products | C72: Utility/maintenance | D72: 13 | E72: PRODUCT | F72: =COUNTIF(Rules!$B$2:$B$1568,A72) -> 1 | G72: =COUNTIFS(Rules!$B$2:$B$1568,A72,Rules!$H$2:$H$1568,"QUESTION") -> 0 | H72: One-off copy of IVMST attr 29 UPC into attr 51 W.UPC/EAN for a select list. | I72: reads IVMST · writes IVMST | J72: none | K72: Uses default-file OPEN/READU syntax with the record ID as file; overwrites any existing EAN.
A73: COPYWD | B73: Products | C73: Outbound-generator | D73: 7 | E73: PRODUCT, PO | F73: =COUNTIF(Rules!$B$2:$B$1568,A73) -> 2 | G73: =COUNTIFS(Rules!$B$2:$B$1568,A73,Rules!$H$2:$H$1568,"QUESTION") -> 1 | H73: Copies working files to web-data copies (IVMST.WD, IVDISC.WD, IVORD.WD, SCANORD.WD) for the member website. | I73: reads IVMST, IVMST.DISC, IVORD, SCANORD · writes IVMST.WD, IVDISC.WD, IVORD.WD, SCANORD.WD | J73: EXECUTE COPY, SSELECT SCANORD | K73: `EXECUTE 'Y'` answers a prompt blindly; SCANORD copy does not overwrite-delete stale web rows.
A74: COUNT.GRPS | B74: Reporting | C74: Report/print | D74: 44 | E74: PRODUCT | F74: =COUNTIF(Rules!$B$2:$B$1568,A74) -> 2 | G74: =COUNTIFS(Rules!$B$2:$B$1568,A74,Rules!$H$2:$H$1568,"QUESTION") -> 1 | H74: For a trade show, counts how many distinct E-groups each member bought in a date range (TEMPDATA). | I74: reads ARHIST, IVMST, IVMST.DISC · writes TEMPDATA (cleared) | J74: EXECUTE CLEAR-FILE, SSELECT ARHIST, SELECT TEMPDATA | K74: Blank E-group indexes value position "" (adds to value 0/1 depending on runtime); E-groups > 70 ignored; 800-line cap.
A75: COUNTRY | B75: Products | C75: Subroutine | D75: 18 | E75: PRODUCT | F75: =COUNTIF(Rules!$B$2:$B$1568,A75) -> 1 | G75: =COUNTIFS(Rules!$B$2:$B$1568,A75,Rules!$H$2:$H$1568,"QUESTION") -> 0 | H75: Translates country-of-origin codes to country names using CONTROL 'COO'. | I75: reads CONTROL ('COO') · writes none | J75: none | K75: Opens and reads CONTROL on every call; CHAIN ABORT on missing COO from inside a subroutine.
A76: CR.CKS | B76: Members | C76: Report/print | D76: 13 | F76: =COUNTIF(Rules!$B$2:$B$1568,A76) -> 1 | G76: =COUNTIFS(Rules!$B$2:$B$1568,A76,Rules!$H$2:$H$1568,"QUESTION") -> 0 | H76: Prints a full page of "X" characters on the laser printer (alignment test for customer rebate checks). | I76: none | J76: none | K76: Name suggests rebate check printing but it is only a test pattern.
A77: CRUPDATE | B77: Members | C77: Interactive | D77: 37 | F77: =COUNTIF(Rules!$B$2:$B$1568,A77) -> 2 | G77: =COUNTIFS(Rules!$B$2:$B$1568,A77,Rules!$H$2:$H$1568,"QUESTION") -> 1 | H77: Updates a member's statement date (LST.STMT) or credit limit (ARMST attr 7). | I77: reads ARMST, LST.STMT · writes ARMST (attr 7), LST.STMT (attr 1) | J77: none | K77: No locking; no audit of credit-limit changes; non-numeric limits accepted.
A78: CS.UPD.UPS | B78: Orders | C78: Outbound-generator | D78: 100 | E78: PO | F78: =COUNTIF(Rules!$B$2:$B$1568,A78) -> 7 | G78: =COUNTIFS(Rules!$B$2:$B$1568,A78,Rules!$H$2:$H$1568,"QUESTION") -> 3 | H78: For a shipped sale transaction (TRANSLOG), appends a UPS WorldShip import line to the DOWNLOADS 'UPS.CSV' staging record and indexes invoice → transaction in UPSIDX. | I78: reads CONTROL ('UPS.HDRS','UPS.SHIP.PRODS','UPS.VALUES','ENCRYPT.CODES'), TRANSLOG, IVCUST · writes DOWNLOADS ('UPS.CSV'), UPSIDX | J78: ENCRYPTOR; INCLUDE CSBP I_CS_COMMON, TRANSLOG.FIELDS, IVCUST.FIELDS (not in extract) | K78: Insurance based on cost not sale; values under INS.MIN declared as $100 rather than INS.MIN; when an alternate ship-to name exists, address/CSZ/phone are taken from shifted fields (ADDR from CSZ<1,3>, CSZ from PHONE<1,3>) — likely wrong; hard-coded default encryption seed.
A79: CUST.RBT | B79: Members | C79: Interactive | D79: 114 | E79: PRODUCT, PRICING | F79: =COUNTIF(Rules!$B$2:$B$1568,A79) -> 5 | G79: =COUNTIFS(Rules!$B$2:$B$1568,A79,Rules!$H$2:$H$1568,"QUESTION") -> 0 | H79: Enters consumer rebate claims for a dealer, prints the consumer rebate check, and voids checks. | I79: reads ARMST, STRNAME, RBTCODES, IVMST, RBTDATA · writes RBTDATA | J79: none | K79: Auto-incremented check # is not checked against existing RBTDATA (overwrite risk); L54 missing OR (syntax); "E" at name prompt loops instead of exiting; no AP/GL posting of rebate payments; void amount stored as string "-nnn".
A80: CUST.RBT.CHKS | B80: AP | C80: Report/print | D80: 70 | E80: PRODUCT | F80: =COUNTIF(Rules!$B$2:$B$1568,A80) -> 5 | G80: =COUNTIFS(Rules!$B$2:$B$1568,A80,Rules!$H$2:$H$1568,"QUESTION") -> 2 | H80: Reprints/prints consumer rebate checks from RBTDATA for a check-number range not yet flagged printed. | I80: reads RBTDATA, IVMST · writes RBTDATA (attr 7 PRINTED flag) | J80: EXECUTE SSELECT RBTDATA | K80: Printed flag written before print; `CHKN0` (zero) typo var unused.
A81: CUST.RBT.LJ | B81: AP | C81: Interactive | D81: 114 | E81: PRODUCT | F81: =COUNTIF(Rules!$B$2:$B$1568,A81) -> 9 | G81: =COUNTIFS(Rules!$B$2:$B$1568,A81,Rules!$H$2:$H$1568,"QUESTION") -> 1 | H81: Enter a consumer rebate (dealer, rebate code, products, consumer address), store in RBTDATA and print the rebate check on a LaserJet; also voids checks. | I81: reads ARMST, STRNAME, RBTCODES, IVMST, RBTDATA · writes RBTDATA | J81: none | K81: L64 `IF ZIP = 'E' ZIP='END'` missing OR (syntax/logic bug); CUSTRBT.LJ is a near-duplicate.
A82: CUSTRBT.LJ | B82: AP | C82: Test-variant | D82: 114 | E82: PRODUCT | F82: =COUNTIF(Rules!$B$2:$B$1568,A82) -> 2 | G82: =COUNTIFS(Rules!$B$2:$B$1568,A82,Rules!$H$2:$H$1568,"QUESTION") -> 1 | H82: Duplicate of CUST.RBT.LJ (consumer rebate entry + check print) with a different check layout including a MICR line. | I82: reads ARMST, STRNAME, RBTCODES, IVMST, RBTDATA · writes RBTDATA | J82: none | K82: Fixes the L64 ZIP OR bug of CUST.RBT.LJ (L66 has OR). Which of the two is live is unknown.
A83: CUSTRBT.NEW | B83: AP | C83: Test-variant | D83: 92 | E83: PRODUCT | F83: =COUNTIF(Rules!$B$2:$B$1568,A83) -> 1 | G83: =COUNTIFS(Rules!$B$2:$B$1568,A83,Rules!$H$2:$H$1568,"QUESTION") -> 0 | H83: Copy of CUST.RBT.LJ that records consumer rebates in RBTDATA without printing a check (checks printed later by CUST.RBT.CHKS). | I83: reads ARMST, STRNAME, RBTCODES, IVMST, RBTDATA · writes RBTDATA | J83: none | K83: L62 `IF STATE = 'E' STATE='END'` missing OR. Unused PCL vars/FORM array left over.
A84: CUSTRBTNEW1 | B84: AP | C84: Test-variant | D84: 79 | E84: PRODUCT | F84: =COUNTIF(Rules!$B$2:$B$1568,A84) -> 2 | G84: =COUNTIFS(Rules!$B$2:$B$1568,A84,Rules!$H$2:$H$1568,"QUESTION") -> 1 | H84: Variant of CUSTRBT.NEW that takes the next rebate check number from CONTROL instead of operator entry; no void function. | I84: reads ARMST, STRNAME, RBTCODES, IVMST, CONTROL · writes RBTDATA, CONTROL | J84: none | K84: Counter only persisted on clean exit (crash/disconnect reuses numbers); two users would share/collide; L57 STATE OR bug.
A85: DEL.ARINV | B85: AR | C85: Utility/maintenance | D85: 42 | F85: =COUNTIF(Rules!$B$2:$B$1568,A85) -> 4 | G85: =COUNTIFS(Rules!$B$2:$B$1568,A85,Rules!$H$2:$H$1568,"QUESTION") -> 1 | H85: Deletes one open invoice from a member's ARINV record and backs its open balance out of ARMST aging buckets. | I85: reads ARMST, ARINV · writes ARMST, ARINV | J85: UPD.ARLOG (commented out) | K85: MATREADU without LOCKED clause conflates locked and not-found (L15,L17); no confirmation before delete; no audit.
A86: DEL.NUMBER | B86: Orders | C86: Utility/maintenance | D86: 24 | E86: PO | F86: =COUNTIF(Rules!$B$2:$B$1568,A86) -> 3 | G86: =COUNTIFS(Rules!$B$2:$B$1568,A86,Rules!$H$2:$H$1568,"QUESTION") -> 2 | H86: Deletes a shipping number record from NUMBER and resets the related vendor order (VNORD) attr 12 to 0. | I86: reads NUMBER, IVORD, ARMST, VNORD · writes NUMBER (delete), VNORD | J86: none | K86: L14 on missing ARMST shows stale/undefined NAME; blank = confirm is dangerous.
A87: DELETE.MEMBER | B87: Members | C87: Utility/maintenance | D87: 46 | F87: =COUNTIF(Rules!$B$2:$B$1568,A87) -> 4 | G87: =COUNTIFS(Rules!$B$2:$B$1568,A87,Rules!$H$2:$H$1568,"QUESTION") -> 4 | H87: Zeroes a member's ARMST balances and deletes the member's ARINV, BVEND, IVEND, IVSOLD detail records (keeps ARMST record). | I87: reads ARMST · writes ARMST, ARINV/BVEND/IVEND/IVSOLD (delete) | J87: UPD.ARLOG (commented out) | K87: Hard-coded passwords in source; no record locking; history destruction with no audit.
A88: DH$ | B88: Utility | C88: Utility/maintenance | D88: 53 | F88: =COUNTIF(Rules!$B$2:$B$1568,A88) -> 1 | G88: =COUNTIFS(Rules!$B$2:$B$1568,A88,Rules!$H$2:$H$1568,"QUESTION") -> 0 | H88: Test harness that converts an amount in cents to check-writing words using word table CONTROL 'MONEY'. | I88: reads CONTROL ('MONEY') · writes none | J88: none | K88: L47 tests BUCKS=1 after BUCKS has been truncated, so e.g. $101 prints "Dollar"; interactive input meant to be replaced (L15 comment).
A89: DH1 | B89: Products | C89: Batch | D89: 61 | E89: PRODUCT, PO | F89: =COUNTIF(Rules!$B$2:$B$1568,A89) -> 5 | G89: =COUNTIFS(Rules!$B$2:$B$1568,A89,Rules!$H$2:$H$1568,"QUESTION") -> 5 | H89: 1985 suggested-order calculator: for a product group, computes reorder quantity from monthly sales history and writes it to ORDER file. | I89: reads IVMST, CONTROL ('UPD') · writes ORDER (optionally CLEARFILE) | J89: EXECUTE SSELECT IVMST WITH GRP | K89: L14 says wait 10-@DAY days but the test is @DAY<20; attr 2 usage conflicts with dict name ORD.QTY; HALF logic L51 likely wrong (I=B+1 after loop). Likely OBSOLETE overall (1985).
A90: DIVD.CHK.LJ | B90: Members | C90: Report/print | D90: 80 | F90: =COUNTIF(Rules!$B$2:$B$1568,A90) -> 9 | G90: =COUNTIFS(Rules!$B$2:$B$1568,A90,Rules!$H$2:$H$1568,"QUESTION") -> 4 | H90: Prints annual patronage dividend checks (with stub) for members in STOCK with a dividend, and records each check in APBR. | I90: reads STOCK, ARMST, ARMST2 · writes APBR | J90: EXECUTE SSELECT STOCK WITH DIV40 GT 0 BY NAME; TERM | K90: Zero/negative paid amounts still print (selection is on DIV40 not PAID); totals page printed on a check stock form and also written to APBR under next check #.
A91: DRAW.BOX | B91: Utility | C91: Subroutine | D91: 29 | F91: =COUNTIF(Rules!$B$2:$B$1568,A91) -> 1 | G91: =COUNTIFS(Rules!$B$2:$B$1568,A91,Rules!$H$2:$H$1568,"QUESTION") -> 0 | H91: Draws a box on the terminal using per-terminal graphics chars from TERMINALS. | I91: reads TERMINALS · writes none | J91: none | K91: none
A92: DSP.REPORT | B92: Utility | C92: Subroutine | D92: 37 | F92: =COUNTIF(Rules!$B$2:$B$1568,A92) -> 1 | G92: =COUNTIFS(Rules!$B$2:$B$1568,A92,Rules!$H$2:$H$1568,"QUESTION") -> 0 | H92: Pages a field-mark-delimited report on screen 21 lines at a time with Back/End/custom prompt. | I92: none | J92: none | K92: none
A93: EDI.CREDIT | B93: EDI | C93: Staging-processor | D93: 194 | E93: VENDOR, PRICING | F93: =COUNTIF(Rules!$B$2:$B$1568,A93) -> 14 | G93: =COUNTIFS(Rules!$B$2:$B$1568,A93,Rules!$H$2:$H$1568,"QUESTION") -> 7 | H93: Parses vendor credit memos from staging record EDI 'CREDITS' (for non-PRO "MDS" billing) and writes one EDICREDITS record per credit with computed terms and surcharge. | I93: reads EDI ('CREDITS','ERROR'), CONTROL ('UPD','DAYS','EDIC'), APMST, VNIDX, VNMST, ARMST, VENDORD · writes EDICREDITS, EDI ('ERROR', 'CREDITS' rewritten then deleted), CONTROL ('EDIC') | J93: none | K93: AGING (L162), NET, APAMT computed but unused; empty IF at L40-41; AMT taken from <8> as-is with ICONV MD2 (input dollars, stored cents); ERRS/GCTOT not initialized; RELEASE of ARMST/VENDORD never locked; on APMST error EDI 'CREDITS' rewritten with the remaining (not current) data.
A94: EDI.CREDITS | B94: EDI | C94: Test-variant | D94: 343 | E94: VENDOR, PO, PRICING | F94: =COUNTIF(Rules!$B$2:$B$1568,A94) -> 23 | G94: =COUNTIFS(Rules!$B$2:$B$1568,A94,Rules!$H$2:$H$1568,"QUESTION") -> 13 | H94: Older (11/2001) copy of EDI.UPDATE, the EDI drop-ship ("non-PRO MDS") billing run; rules listed in full because it was read before EDI.UPDATE, see EDI.UPDATE for the current logic: parses vendor invoices from staging record EDI 'DATA', bills members in AR (ARINV/ARSHIP/ARMST), books AP (APDIST/APHIST/APMST), updates vendor and PO-tracking totals; negative invoices are parked in EDICREDITS. | I94: reads EDI ('DATA','ERROR'), CONTROL ('UPD','APBAT','APPER','DAYS','NEXT.EDICR','INV','MS'), APMST, VNIDX, VNMST, ARMST, VENDORD, APHIST, ARINV, IVEND · writes EDI ('DATA','ERROR', delete 'DATA'), EDICREDITS, CONTROL ('APBAT','NEXT.EDICR','INV','MS'), APMST, VNMST, VENDORD, IVEND, ARMST, APDIST, APHIST, ARINV, ARSHIP | J94: none | K94: VDISC reused as both vendor discount rate (L225) and discount accumulator (L279), so A/P DISC total is wrong; first GOSUB 55 uses unassigned VEND; ARINV MATREADU (L287) has no LOCKED clause (silent fallthrough); shipping is not added to AMT (L224 commented) but is listed on ARSHIP; on vendor/member error the remaining queue (not the bad invoice) is rewritten to EDI 'DATA'; EDICREDITS gets raw EDI text here but a structured record from EDI.CREDIT (two layouts in one file).
A95: EDI.UPDATE | B95: EDI | C95: Staging-processor | D95: 413 | E95: VENDOR, PO, PRICING | F95: =COUNTIF(Rules!$B$2:$B$1568,A95) -> 30 | G95: =COUNTIFS(Rules!$B$2:$B$1568,A95,Rules!$H$2:$H$1568,"QUESTION") -> 12 | H95: Current EDI drop-ship ("non-PRO MDS") billing run: validates and posts vendor invoices from staging record EDI 'DATA' to member AR (ARINV/ARSHIP/ARMST) and vendor AP (APDIST/APHIST/APMST), tracks PO billing, then chains EDI.CREDIT for credit invoices. | I95: reads EDI ('DATA'), CONTROL ('UPD','APBAT','APPER','INV','MS'), APMST, VNIDX, VNMST, ARMST, VENDORD, APHIST, ARINV, IVEND · writes EDI ('DATA','ERROR','EDIAMTS','CREDITS','EDIVEND','EDITERMS','EDIDUPS'), CONTROL, APMST, VNMST, VENDORD, IVEND, ARMST, APDIST, APHIST, ARINV, ARSHIP, EDILOG | J95: EXECUTE RUN BP EDI.CREDIT (when credits found) | K95: L129 increments ERR not ERRS so amount-mismatch errors are not counted/listed; VDISC reused as rate and accumulator so A/P DISC total wrong; ARINV MATREADU (L349) no LOCKED clause; CLOSED.MN uninitialized; first GOSUB 55 with unassigned VEND; operator-contact comment with phone number at L80; IVEND READU has no lock handling.
A96: EDIT.LINE | B96: Utility | C96: Subroutine | D96: 75 | F96: =COUNTIF(Rules!$B$2:$B$1568,A96) -> 1 | G96: =COUNTIFS(Rules!$B$2:$B$1568,A96,Rules!$H$2:$H$1568,"QUESTION") -> 0 | H96: Raw-keystroke full-line editor for green-screen input fields (insert/overtype, arrows, ESC/up exit). | I96: none | J96: INCLUDE BP I_RAWINP | K96: none material.
A97: EGRP.SALES | B97: Reporting | C97: Batch | D97: 45 | E97: PRODUCT | F97: =COUNTIF(Rules!$B$2:$B$1568,A97) -> 4 | G97: =COUNTIFS(Rules!$B$2:$B$1568,A97,Rules!$H$2:$H$1568,"QUESTION") -> 2 | H97: Rebuilds EGRPSLS: per-member sales totals by product e-group (IVMST attr 39 EGRP) for a date range from ARHIST. | I97: reads ARHIST, IVMST, IVMST.DISC · writes EGRPSLS (cleared first) | J97: EXECUTE CLEAR-FILE DATA EGRPSLS; SSELECT ARHIST | K97: TD(76)<1,PROD>=1 uses product number as a value position (huge sparse records); DIM TD(100) breaks if EGRP > 100 or collides with 75/76; an empty record is written for key '' on the first member; OPEN failures only print and continue.
A98: EM.1 | B98: Members | C98: Interactive | D98: 17 | E98: PRICING | F98: =COUNTIF(Rules!$B$2:$B$1568,A98) -> 2 | G98: =COUNTIFS(Rules!$B$2:$B$1568,A98,Rules!$H$2:$H$1568,"QUESTION") -> 1 | H98: Enter a member's sales amount and rebate percentage to compute a vendor-rebate check amount stored in MISC. | I98: reads ARMST · writes MISC | J98: none | K98: No input validation; overwrites prior MISC values. Later version of ENTER.MISC.
A99: EMAIL.FSINV | B99: AR | C99: Outbound-generator | D99: 28 | F99: =COUNTIF(Rules!$B$2:$B$1568,A99) -> 2 | G99: =COUNTIFS(Rules!$B$2:$B$1568,A99,Rules!$H$2:$H$1568,"QUESTION") -> 0 | H99: Builds an 'email.bat' command line in the FSINV directory file to email an FSINV invoice attachment via the ericmail utility. | I99: reads/writes FSINV ('email.bat') | J99: none (DOS execute commented out) | K99: Execute is commented out, so no email is sent from here; IDATE param unused.
A100: EMAIL.INVOICES | B100: AR | C100: Outbound-generator | D100: 41 | F100: =COUNTIF(Rules!$B$2:$B$1568,A100) -> 3 | G100: =COUNTIFS(Rules!$B$2:$B$1568,A100,Rules!$H$2:$H$1568,"QUESTION") -> 0 | H100: Builds INVOICES.DBF (email notification feed) listing invoice PDF URLs per member for invoices posted on a given date. | I100: reads WEBSTMT (ARHIST opened, unused) · writes INVOICES.DBF (cleared first) | J100: EXECUTE CLEAR-FILE, SSELECT WEBSTMT | K100: L35 `IF ... COUNT = COUNT + 1` lacks THEN; no header comment/date.
...
